Workbook
Name Capacity_Factor: Inputs_Assumptions!$E$29
Name Capacity_per_Turbine: Inputs_Assumptions!$E$26
Name CfD_Expiry_Date: Inputs_Assumptions!$E$99
Name CfD_Strike_Price: Inputs_Assumptions!$E$119
Name Circ_Ref: Inputs_Assumptions!#REF!
Name Constr_Contingency: Inputs_Assumptions!#REF!
Name Constr_Cost_per_kW: Inputs_Assumptions!#REF!
Name Constr_Debt_Pct: Inputs_Assumptions!$E$162
Name Constr_End_Date: Inputs_Assumptions!$E$83
Name Constr_Interest_Rate: Inputs_Assumptions!$E$163
Name Constr_P1: Inputs_Assumptions!$E$85
Name Constr_P2: Inputs_Assumptions!$E$86
Name Constr_P3: Inputs_Assumptions!$E$87
Name Constr_P4: Inputs_Assumptions!$E$88
Name Constr_P5: Inputs_Assumptions!$E$89
Name Constr_P6: Inputs_Assumptions!$E$90
Name Constr_P7: Inputs_Assumptions!$E$91
Name Constr_P8: Inputs_Assumptions!$E$92
Name Constr_Start_Date: Inputs_Assumptions!$E$82
Name Constr_Start_Quarter: Inputs_Assumptions!$E$84
Name Contigency: Inputs_Assumptions!$E$110
Name CPI_Escalation: Inputs_Assumptions!$E$127
Name Days_in_Year: Inputs_Assumptions!$E$15
Name DC_Cost_per_kW: Inputs_Assumptions!$E$104
Name Debt_Refinance_Date: Inputs_Assumptions!$E$98
Name Debt_Tenor: Inputs_Assumptions!$E$174
Name Degradation_Factor: Inputs_Assumptions!$E$76
Name Depr_Rate_Annual: Inputs_Assumptions!$E$135
Name Devex_Cost_per_kW: Inputs_Assumptions!$E$104
Name Electr_Rate: Inputs_Assumptions!$E$145
Name Electr_Rate_Escalation: Inputs_Assumptions!$E$157
Name Equity_In_Project: Inputs_Assumptions!$E$103
Name FID_Date: Inputs_Assumptions!$E$79
Name First_Debt_Interest: Inputs_Assumptions!$E$177
Name First_Interest_Quarterly: Inputs_Assumptions!$E$178
Name Fixed_Costs: Inputs_Assumptions!#REF!
Name Fixed_Escalation: Inputs_Assumptions!#REF!
Name Hours: Inputs_Assumptions!$E$11
Name Loan_Cmt_Fee_Pct: Inputs_Assumptions!$E$168
Name Loan_Upfront_Fee_Pct: Inputs_Assumptions!$E$167
Name Max_Debt_Draw: Inputs_Assumptions!$E$165
Name Merchant_Price: Inputs_Assumptions!$E$120
Name Million: Inputs_Assumptions!$E$24
Name Min_LLCR: Inputs_Assumptions!$E$186
Name Months_in_Quarter: Inputs_Assumptions!$E$12
Name Months_in_Year: Inputs_Assumptions!$E$13
Name Op_End_Date: Inputs_Assumptions!$E$101
Name Op_Start_Date: Inputs_Assumptions!$E$97
Name Oper_Debt_Pct: Inputs_Assumptions!#REF!
Name Operating_Debt_Pct: Inputs_Assumptions!#REF!
Name Quarters_in_Year: Inputs_Assumptions!$E$14
Name Refi_Q_Num: IRR_Revenue_Model!$E$13
Name Revenue_Escalation: Inputs_Assumptions!$E$126
Name RPI_Escalation: Inputs_Assumptions!$E$128
Name Scenario: Inputs_Assumptions!$E$141
Name Second_Debt_Interest: Inputs_Assumptions!$E$181
Name Second_Interest_Quarterly: Inputs_Assumptions!$E$182
Name Tax_Rate: Inputs_Assumptions!$E$22
Name Terminal_Exit_Date: Inputs_Assumptions!$E$100
Name Turbine_Min_Pct: Inputs_Assumptions!#REF!

Sheet Inputs_Assumptions
B2: =E7&" - Development and IRR Analysis" -> Norfolk Vanguard West - Development and IRR Analysis
B4: Development and Operating Assumptions: | D4: Units: | G4: Source | H4: Page Number | I4: Comments | J4: Link
C6: Project Name, Units, and Production Drivers:
C7: Project Name: | D7: Name | E7: Norfolk Vanguard West
C8: Asset Type: | D8: Name | E8: Energy
C9: Location: | D9: Name | E9: Norfolk England
C11: Hours in Day: | D11: # | E11: 24
C12: Months in Quarter: | D12: # | E12: 3
C13: Months in Year: | D13: # | E13: 12
C14: Quarters in Year: | D14: # | E14: 4
C15: Days in Year: | D15: # | E15: 365
C17: Hours in Q1: | D17: # | E17: 2160
C18: Hours in Q2: | D18: # | E18: 2184
C19: Hours in Q3: | D19: # | E19: 2208
C20: Hours in Q4: | D20: # | E20: 2208
C22: Tax Rate: | D22: % | E22: 0.25 | I22: UK corporation tax rate for profits over £250,000
C23: Units (kW to MW): | D23: # | E23: 1000
C24: Units (Million): | D24: # | E24: 1000000
C26: Installed Capacity per Turbine: | D26: MW | E26: 15 | G26: RWE Press Release | I26: Vestas V236-15.0 MW offshore wind turbines | J26: https://www.rwe.com/en/press/rwe-offshore-wind-gmbh/2026-02-20-rwe-and-vestas-agree-turbine-supply-agreement-for-vanguard-west-offshore-wind-farm/
C27: # of Turbines: | D27: # | E27: 103 | G27: RWE Press Release | I27: Number increased from press release to account for Unit B and Unit C | J27: https://www.rwe.com/en/press/rwe-offshore-wind-gmbh/2026-02-20-rwe-and-vestas-agree-turbine-supply-agreement-for-vanguard-west-offshore-wind-farm/
C28: Installed Capacity of Wind Farm | D28: MW | E28: =Capacity_per_Turbine*Turbines -> 1545 | I28: Unit A, B and C have 1380, 90 and 75 MW respectively
C29: Net Capacity Factor: | D29: % | E29: 0.505 | G29: DESNZ Arup Report | H29: 6, 23 | I29: Accounts for all relevant loss factors, including system availability (Wind Turbine Generator (WTG), Balance of Plant (BoP), and Grid), wake losses (internal and external), electrical system losses, turbine performance losses, and other secondary factor | J29: https://assets.publishing.service.gov.uk/media/6966a5c7e8c04eb2919f773d/lcoe-2024-offshore-wind.pdf
C30: Annual Gross Energy Output per Turbine: | D30: MWh | E30: =Capacity_per_Turbine*Hours*Days_in_Year -> 131400 | I30: Theoretical maximum energy produced if every turbine operated perfectly, with no losses, downtime, interference
C31: Annual Net Energy Output per Turbine: | D31: MWh | E31: =E30*Capacity_Factor -> 66357
C33: Initial Output Standard Deviation ("Uncertainty"): | D33: # | E33: 0.072 | G33: Published UK Offshore Wind Research | I33: Given revenue is almost entirely a function of how much wind blows which is uncertain, a P-value framework is used to quantify the uncertainty (via treating annual energy output probability distribution = If you modelled the annual energy output over 1000s of hypothetical years). IAV uncertainty of 4% (Potisomporn et al. 2022, UK Offshore specific) and model uncertainty of 6% (conservative mid-point, Lee & Fields 2021) combined give you a uncertainty of 7% | J33: https://docs.nlr.gov/docs/fy21osti/79631.pdf
C34: Turbine Net Energy Yields (Annual) P50 - 50% | D34: MWh | E34: =E31 -> 66357 | F34: =6827/Turbines -> 66.281553 | G34: =E34*Turbines/1000 -> 6834.771 | I34: For equity IRR and headline return to investors and investment thesis. Represents the expected outcome if you owned an asset across its full lifecycle
C35: Turbine Net Energy Yields (Annual) P75 - 25% | D35: MWh | E35: =_xlfn.NORM.INV(25%,$E$34,$E$33*$E$31) -> 63134.488 | F35: =6495/Turbines -> 63.058252 | G35: =E35*Turbines/1000 -> 6502.8522 | I35: For equity sensitivity analysis. Represents the outcome for a roughly bad year and to check if you still get a acceptable equity return
C36: Turbine Net Energy Yields (Annual) P90 - 10% | D36: MWh | E36: =_xlfn.NORM.INV(10%,$E$34,$E$33*$E$31) -> 60234.126 | F36: =6198/Turbines -> 60.174757 | G36: =E36*Turbines/1000 -> 6204.115 | I36: For debt sizing case. Debt lenders want to ensure the project can service the debt in P90 year (once per decade). The DSCR must be above the covenant floor at event P90
C37: Turbine Net Energy Yields (Annual) P99 - 1% | D37: MWh | E37: =_xlfn.NORM.INV(1%,$E$34,$E$33*$E$31) -> 55242.398 | F37: =5683/Turbines -> 55.174757 | G37: =E37*Turbines/1000 -> 5689.967 | I37: For worst case scenario. Used to answer 2 questions: 1) Can the project survive a P99 year without breaching debt covenants or requiring equity payments 2) Does the project generate enough cash flow to cover fixed obligations (debt service, O&M, insurance) without drawing on reserves
C38: Turbine Net Energy Yields (Annual) P50 - 50% | D38: % | E38: =E34/$E$34 -> 1
C39: Turbine Net Energy Yields (Annual) P75 - 25% | D39: % | E39: =E35/$E$34 -> 0.95143674
C40: Turbine Net Energy Yields (Annual) P90 - 10% | D40: % | E40: =E36/$E$34 -> 0.90772829
C41: Turbine Net Energy Yields (Annual) P99 - 1% | D41: % | E41: =E37/$E$34 -> 0.83250295
C43: Production Seasonality Avg Load Factor (Q1) | D43: % | E43: 0.483 | G43: DESNZ Energy Trends: UK Renewables | H43: Tab 6_1 | I43: Average offshore wind load factors used from 2015 Q2 to 2025 Q3 where offshore wind capacity is > 5GW | J43: https://www.gov.uk/government/statistics/energy-trends-section-6-renewables
C44: Production Seasonality Avg Load Factor (Q2) | D44: % | E44: 0.303 | G44: DESNZ Energy Trends: UK Renewables | H44: Tab 6_1 | I44: Average offshore wind load factors used from 2015 Q2 to 2025 Q3 where offshore wind capacity is > 5GW | J44: https://www.gov.uk/government/statistics/energy-trends-section-6-renewables
C45: Production Seasonality Avg Load Factor (Q3) | D45: % | E45: 0.305 | G45: DESNZ Energy Trends: UK Renewables | H45: Tab 6_1 | I45: Average offshore wind load factors used from 2015 Q2 to 2025 Q3 where offshore wind capacity is > 5GW | J45: https://www.gov.uk/government/statistics/energy-trends-section-6-renewables
C46: Production Seasonality Avg Load Factor (Q4) | D46: % | E46: 0.487 | G46: DESNZ Energy Trends: UK Renewables | H46: Tab 6_1 | I46: Average offshore wind load factors used from 2015 Q2 to 2025 Q3 where offshore wind capacity is > 5GW | J46: https://www.gov.uk/government/statistics/energy-trends-section-6-renewables
C48: Production Generation Index (Q1) | D48: hours | E48: =E43*E17 -> 1043.28 | I48: 2160 hours in Q1
C49: Production Generation Index (Q2) | D49: hours | E49: =E44*E18 -> 661.752 | I49: 2184 hours in Q2
C50: Production Generation Index (Q3) | D50: hours | E50: =E45*E19 -> 673.44 | I50: 2208 hours in Q3
C51: Production Generation Index (Q4) | D51: hours | E51: =E46*E20 -> 1075.296 | I51: 2208 hours in Q4
C53: Production Seasonality Profile (Q1) | D53: % | E53: =E48/SUM($E$48:$E$51) -> 0.30207009
C54: Production Seasonality Profile (Q2) | D54: % | E54: =E49/SUM($E$48:$E$51) -> 0.19160291
C55: Production Seasonality Profile (Q3) | D55: % | E55: =E50/SUM($E$48:$E$51) -> 0.19498704
C56: Production Seasonality Profile (Q4) | D56: % | E56: =E51/SUM($E$48:$E$51) -> 0.31133996
C58: Negative Annual Revenue Loss (2029-2032) | D58: % | E58: 0.025 | G58: Assumption | I58: From AR4 onwards, the government's negative pricing rule is such that generators are not paid any difference payments when the Intermittent Market Reference Price (IMPR) is negative for any single hour. The IMPR is the reference price that is set for each hour based on the results of auctions for power held, the generation weighted day-ahead. This is not the intraday or balancing market price. GB negative price hours: 2021 = 7 (0.08%), 2022 = 29 (0.33%), 2023 = 107 (1.22%), 2024 = 155 (1.77%), 2025 = 150-180 (estimated). Using this the values for the negative annual revenue loss has been estimated
C59: Negative Annual Revenue Loss (2033-2037) | D59: % | E59: 0.035 | G59: Assumption
C60: Negative Annual Revenue Loss (2038-2044) | D60: % | E60: 0.05 | G60: Assumption
C61: Negative Annual Revenue Loss (2045-2049) | D61: % | E61: 0.065 | G61: Assumption
C62: Negative Annual Revenue Loss (2050-Beyond) | D62: % | E62: 0.08 | G62: `
C63: Negative Annual Revenue Loss Period 1 End Date | D63: Date | E63: =DATE(2033,1,1) -> 48580
C64: Negative Annual Revenue Loss Period 2 End Date | D64: Date | E64: =DATE(2038,1,1) -> 50406
C65: Negative Annual Revenue Loss Period 3 End Date | D65: Date | E65: =DATE(2045,1,1) -> 52963
C66: Negative Annual Revenue Loss Period 4 End Date | D66: Date | E66: =DATE(2050,1,1) -> 54789
C67: Negative Annual Revenue Loss Period 5 End Date | D67: Date | E67: =DATE(2064,1,1) -> 59902
C69: Curtailment Period 1 (2029-2034) | D69: % | E69: 0.0035 | G69: Assumption | I69: Economic curtailment as the transmission network cannot physically accept all the power being generated. Therefore the generator cannot export to the grid. However GB curtailment problem is almost entirely a Scottish problem given 98% of the total constrained volume arises from Scottish wind farms. The Norfolk Vanguard project is in East Anglia and not a constrained zone given its proximity to demand centres. However the East Anglia corridor does face growing congestion risk as the large cluster of offshore wind farms grows which all connect into broadly the same corridor (Norfolk Vanguard East, East Anglia Two, East Anglia Three, Boreas). This value should be applied to AEP
C70: Curtailment Period 2 (2035-2044) | D70: % | E70: 0.01 | G70: Assumption
C71: Curtailment Period 3 (2045 and beyond) | D71: % | E71: 0.015 | G71: Assumption
C72: Curtailment Period 1 End Date | D72: Date | E72: =DATE(2035,1,1) -> 49310
C73: Curtailment Period 2 End Date | D73: Date | E73: =DATE(2045,1,1) -> 52963
C74: Curtailment Period 3 End Date | D74: Date | E74: =DATE(2064,1,1) -> 59902
C76: Annual Degradation Factor: | D76: % | E76: =E155 -> 0.002 | I76: Base case given modern offshore wind turbines and proactive O&M (which would preserve output). Use 0.5% as a conservative case
C78: Development & Construction Assumptions:
C79: Financial Investment Decision: | E79: 46203 | G79: RWE press release | I79: RWE is currently targeting a FID for both Vanguard projects in summer 2026
C81: Construction Period: | D81: # Quarters | E81: 11
C82: Construction Start: | D82: Date | E82: 46204 | G82: RWE press release
C83: Construction End Unit A, B and C: | D83: Date | E83: 47208 | I83: Assume all work is completed by Q1 2029 (taking into account weather windows, vessel availability, seasonal constraints). AR7 results note 2028/29
C84: Construction Start Quarter: | D84: # | E84: 3
C85: Construction Period 1 | D85: Date / Turbines Installed | E85: 46568 | F85: 6 | G85: Assumption | I85: Construction ramp rate greater in the spring/summer windows. These date also reflect when the turbines are installed and commissioned
C86: Construction Period 2 | D86: Date / Turbines Installed | E86: 46660 | F86: 22 | G86: Assumption
C87: Construction Period 3 | D87: Date / Turbines Installed | E87: 46752 | F87: 30 | G87: Assumption
C88: Construction Period 4 | D88: Date / Turbines Installed | E88: 46843 | F88: 37 | G88: Assumption
C89: Construction Period 5 | D89: Date / Turbines Installed | E89: 46934 | F89: 60 | G89: Assumption
C90: Construction Period 6 | D90: Date / Turbines Installed | E90: 47026 | F90: 85 | G90: Assumption
C91: Construction Period 7 | D91: Date / Turbines Installed | E91: 47118 | F91: 97 | G91: Assumption
C92: Construction Period 8 | D92: Date / Turbines Installed | E92: 47208 | F92: 103 | G92: Assumption
C93: Average installation rate of turbines | D93: # / Month | E93: 4 | G93: Assumption | I93: Calculated from the construction schedule
C95: Operation Period: | D95: # Years | E95: 30 | G95: Assumption | I95: Conservative number which is likely used for evaluation purposes, even though DESNZ-Arup article notes 35 years (which is what developers told they are designing to but perhaps not modelling or likely to be the operational window that lenders are comfortable with
C96: CfD Period: | D96: # Years | E96: 20
C97: Commercial Operation Start: | D97: Date | E97: =Constr_P1 -> 46568 | I97: Under the CfD contract, each turbine becomes eligible for CfD difference payments from the date of its individual commissioning certificate, and not from the project-wide COD date. This means revenue but also costs can start flowing through the offshore construction phase
C98: Debt Refinancing Period | D98: Date | E98: =EDATE(Constr_P8,1*Months_in_Year) -> 47573
C99: CfD Expiry Date: | D99: Date | E99: =EDATE(Constr_P8,E96*Months_in_Year) -> 54513 | I99: CfD expire and the project transitions to merchant pricing for the remaining operating life
C100: Terminal Exit Date: | D100: Date | E100: 49034 | G100: Assumption | I100: Exit timing of PE firm is normally completed within first 5-7 years of operations as PE firms look to extract a dividend to equity at refinancing which is the primary mechanism through which PE sponsors accelerate infrastructure returns. Also a PE firm's equity IRR is a function of when they crystallise the exit multiple, not just the absolute quantum. Selling at 12–14x EBITDA in year 3 of operations (with 17 years of CfD remaining) generates a vastly higher equity IRR than selling at 10× in year 10, even though the total cash returned might be similar. Furthermore Post-COD with 1–2 years of operational data, the asset is perfectly positioned for pension funds, insurance companies, and infrastructure yield vehicles that want low-risk, long-duration, inflation-linked cash flows. These buyers have a lower cost of capital than KKR (they're targeting 5–7% returns vs KKR's 10–12%), so they can pay a premium that generates attractive returns for KKR
C101: Commercial Operation End: | D101: Date | E101: =EDATE(Constr_P8,E95*Months_in_Year) -> 58165 | G101: DESNZ GT Report | I101: 30 year period for the offshore wind farm
C103: Ownership | D103: % | E103: 0.5 | I103: KKR equity stake is 50%
C104: Pre development (Devex) | D104: £/kW | E104: 162 | G104: DESNZ GT Report | H104: 13
C105: Pre-development cost valuation multiple | E105: 2.2 | G105: Assumption | I105: For a project that has secured CfD and nearing FID, the valuation multiples from various sources are: 1) KPMG Offshore Wind in Europe 2019 is 1.5x to 2.5x, 2) Green Giraffe Offshore Wind Finance Update 2019 1.8x to 2.2x, 3) 4C Offshore 2x, 4) FTI Global Wind Market Update 2024 is 1.8x to 2.3x, 5) Wood Mackenzie suggest 1.9x to 2.4x
C106: Purchase price for the offshore wind farm in Devex phase | D106: £M | E106: =DC_Cost_per_kW*Units*Inputs_Assumptions!E28*Inputs_Assumptions!E105*E103/Million -> 275.319 | G106: Calculated | I106: In January 2026, Reuters reported that KKR paid approximately $1.8 billion (£1.43 billion) for a 50% stake in the two Vanguard projects (3.1 GW total). This implies a 100% "Development Equity Value" of roughly £2.86 billion for the two sites at the point of FID. While this provides a reference point, there is only one source and therefore not used
C108: Capital costs during construction (Capex) | D108: £/kW | E108: =E147 -> 2524 | G108: DESNZ GT Report | H108: 4, 13 | I108: Includes project design, procurement, and EPC expenses. In addition, other capital costs such as site works, roads, and utility connection
C109: Infrastructure Costs (Capex) | D109: £/kW | E109: =E148 -> 550 | G109: DESNZ GT Report | H109: 6, 15 | I109: Comprises grid connection expenses (e.g. underground cable costs), the local substation, and transformer stations. The boundary of infrastructure is assumed to include the site where the generator is located, associated electrical infrastructure and connection to the nearest point on the grid. Construction costs for the electricity transmission cable is excluded and included in operating costs (to avoid double counting the cost of offshore transmission assets). IRENA value of 2023 notes infrastructure costs is £437/kW. This has been increased to 550 for 2026 values for a conservative estimate (higher than cumulative inflation rate of 7.62% between 2023 and 2026)
C110: Capex Contingency | D110: % | E110: =E154 -> 0.025 | G110: Green Book | I110: By financial close (when contracts are signed), a residual contingency of 5–10% of contracted CAPEX remains appropriate for uncontracted items, owner's costs, and unforeseen condition. However Arup capital costs include contingency, however there may be a difference between what developers typically spend and what they could be exposed to. Therefore a residual value of 2.5% is used in the base case
C112: Insurance (Opex) | D112: k£/MW/Year | E112: 9.8 | G112: DESNZ GT Report | H112: 18 | I112: Cost of insuring the generation plant, protecting against risks associated with its operation and maintenance
C113: Connection and UoS charges (Opex) | D113: k£/MW/Year | E113: =E153 -> 72 | G113: DESNZ Arup Report, NESO | H113: 6, 29 | I113: Main component is the Offshore Local TnUoS (OFTO charge), where Offshore Transmission Owners (OFTOs) operate and maintain offshore electric power transmission infrastructure delivering electrical power from offshore wind farms to the National Grid. Weighted average is taken for these OFTO costs (for 26/27) based on their capacity and used to sense check Arup number: - East Anglia 1: 714 MW = 13.794649 + 58.160449 = 71.955098 £/kW = 51,375 (weighted contribution £/kW x MW) - Sheringham Shoal: 317 MW = 34.666415 + 40.811823 = 75.478238 £/kW = 23,926 (weighted contribution £/kW x MW) - Dudgeon: 402 MW = 22.039112 + 34.557346 = 56.595458 £/kW = 22,751 (weighted contribution £/kW x MW) Taking a weighted average results in a £63.4/kW or £63.4k/MW/annum (98,052 / 1545 MW). NESO comparables analysis yields £63.4 k/MW/a but these projects have significantly shorter cable runs (22–45km vs 125km for Norfolk Vanguard). East Anglia 1 project value has been used as the project is similar in size (714 MW) and the length of the offshore connection is similar 73/47km offshore + 60km onshore vs 85 km offshore + 37km onshore) | J113: https://www.neso.energy/document/362106/download
C114: O&M (Opex) | D114: k£/MW/Year | E114: =E152 -> 41 | G114: DESNZ GT Report | H114: 18 | I114: Fixed (e.g. labour, planned maintenance, a limited number of unplanned maintenance activities, spares, and consumables) and variable (related to output and include additional O&M expenditures, although these are generally not significant to renewable energy projects) O&M have been combined into a single O&M figure. Arup noted that fixed O&M costs to decrease by 5.5% of 2023 values in 2025, however this was not considered given O&M costs are not broken down between fixed and variable
C115: Seabed lease (Opex) | D115: k£/MW/Year | E115: =4 -> 4 | G115: Assumption | I115: Expenses associated with leasing seabed areas from The Crown Estate for the installation and operation of offshore wind turbines. This project was first owned by Vattenfall when they secured the seabed license in the UK Offshore Wind Leasing Round 3 by The Crown Estate. There are no values for Round 3, but it is noted that the seabed lease costs are significantly lower than the Round 4 costs which were £82,552/MW/year for RWE or £83,000/MW/year for Total. Assume Round 3 is 5% o the costs of Round 4 | J115: https://www.rwe.com/en/press/rwe-renewables/2021-02-08-rwe-successful-in-offshore-wind-leasing-round-4/ | K115: https://www.offshorewind.biz/2021/02/08/total-gig-move-through-uks-leasing-round-4-with-1-5-gw-project/
C116: Route to market fee (Opex) | D116: £/MWh | E116: 2 | G116: Veyt Modelling | I116: The generator physically delivers power into the grid. The route-to-market PPA counterparty buys that power and pays the generator the PPA price for each MWh delivered. Thus, the PPA counterparty provides a commercial service by aggregating the generator's output, managing imbalance exposure, handling settlement, and providing credit support. They charge for this. The fee is typically structured as a deduction from the IMRP. This is because the PPA counterparty takes on the obligation to buy whatever the wind farm actually produces in real time, which will never exactly match the day-ahead forecast. The difference between forecast and actual output in each settlement period creates imbalance charges that the PPA counterparty incurs and typically passes through (partially or fully) to the generator as an additional deduction from the PPA price. Typical RtM fees for UK offshore wind projects currently fall in the range of £1.50 to £3.00/MWh, with most large-scale CfD projects achieving fees closer to £1.50 to £2.00/MWh. Smaller or less established projects, or those with less competitive PPA tender processes, tend to sit at £2.50-£3.00/MWh.The RtM fee tends to be at the lower end of the range for large projects because the sheer volume makes it commercially attractive for PPA counterparties (competitive bidding drives the fee down), and the project's scale allows for portfolio diversification effects within the counterparty's book | J116: https://veyt.com/press-releases/uk-ppa-press-release/
C117: Decommissioning (Opex) | D117: k£/MW | E117: 255 | G117: DESNZ GT Report | H117: 19 | I117: Costs involve the expenses related to safely dismantling and removing infrastructure of an offshore wind farm at the end of its operational life. Arup medium scenario looks low, whereas BVGA/Grant Thornton recommendation is £255/kW.
C119: CfD Strike Price in 2026 | D119: £/MWh | E119: =Electr_Rate -> 94.1184 | G119: DESNZ | H119: 2 | I119: Strike Price for AR7 at 2024 prices is 91.2 £/MWh. OBR CPI rate for 2025 is 3.2%
C120: Wholesale electricity market price in 2026 | D120: £/MWh | E120: =57.8 -> 57.8 | G120: DESNZ Annex M | I120: DESNZ publishes energy and emissions projections based on assumptions of future economic growth, fossil fuel prices, electricity generation costs, and other key variables. The accompanying Annex M provides wholesale electricity price projections under low, central, and high fossil fuel price scenarios. DThe DESNZ reference scenario projects wholesale baseload electricity prices falling steadily, reaching below 5p/kWh (i.e. below £50/MWh) by 2030 in real 2022 terms. This is a reasonable central assumption for the average annual UK wholesale baseload electricity price in the 2050s is approximately £50–60/MWh in 2024 real prices, and so £55/MWh (real 2024) or 57.8 (2026 terms) used as a central case. | J120: https://www.gov.uk/government/publications/energy-and-emissions-projections-2023-to-2050
C121: Merit order discount in 2045-2050 | E121: 0.2 | G121: Assumption | I121: As renewable capacity grows towards 2049, zero-marginal-cost wind and solar increasingly set the wholesale price during daylight and high-wind hours. Gas which currently sets the marginal price for the majority of hours will become progressively smaller share of the dispatch stack. Furthermore given an offshore wind farm doesn't earn the baseload average — it earns the "captured" price, which reflects the fact that it generates most during windy periods when wholesale prices are depressed. Current capture discounts for UK offshore wind are in the range of 10–20% below baseload. By the 2050s, with much higher renewable penetration, this discount is likely to widen. A reasonable assumption is a 15–25% capture discount.Assuming 20% discount
...

Sheet Constr_Phase_Model
B2: Development & Construction Projections
G4: Calendar Year 1: | K4: Calendar Year 2: | O4: Calendar Year 3: | S4: Calendar Year 4: | W4: Calendar Year 5:
B5: Debt and Equity Draws: | D5: =+Inputs_Assumptions!$D$4 -> Units: | E5: Total: | G5: =IRR_Revenue_Model!$G$5 -> 46112 | H5: =IRR_Revenue_Model!$H$5 -> 46203 | I5: =IRR_Revenue_Model!$I$5 -> 46295 | J5: =IRR_Revenue_Model!$J$5 -> 46387 | K5: =IRR_Revenue_Model!$K$5 -> 46477 | L5: =IRR_Revenue_Model!$L$5 -> 46568 | M5: =IRR_Revenue_Model!$M$5 -> 46660 | N5: =IRR_Revenue_Model!$N$5 -> 46752 | O5: =IRR_Revenue_Model!$O$5 -> 46843 | P5: =IRR_Revenue_Model!$P$5 -> 46934 | Q5: =IRR_Revenue_Model!$Q$5 -> 47026 | R5: =IRR_Revenue_Model!$R$5 -> 47118 | S5: =IRR_Revenue_Model!$S$5 -> 47208 | T5: =IRR_Revenue_Model!$T$5 -> 47299 | U5: =IRR_Revenue_Model!$U$5 -> 47391 | V5: =IRR_Revenue_Model!$V$5 -> 47483 | W5: =IRR_Revenue_Model!$W$5 -> 47573 | X5: =IRR_Revenue_Model!$X$5 -> 47664 | Y5: =IRR_Revenue_Model!$Y$5 -> 47756 | Z5: =IRR_Revenue_Model!$Z$5 -> 47848
C7: Construction Period: | D7: # | E7: =COUNTIF(G7:Z7,">0") -> 11 | G7: =IF(AND(G5>Constr_Start_Date,G5<=Constr_P8),1,0) -> 0 | H7: =IF(AND(H5>Constr_Start_Date,H5<=Constr_P8),1,0) -> 0 | I7: =IF(AND(I5>Constr_Start_Date,I5<=Constr_P8),1,0) -> 1 | J7: =IF(AND(J5>Constr_Start_Date,J5<=Constr_P8),1,0) -> 1 | K7: =IF(AND(K5>Constr_Start_Date,K5<=Constr_P8),1,0) -> 1 | L7: =IF(AND(L5>Constr_Start_Date,L5<=Constr_P8),1,0) -> 1 | M7: =IF(AND(M5>Constr_Start_Date,M5<=Constr_P8),1,0) -> 1 | N7: =IF(AND(N5>Constr_Start_Date,N5<=Constr_P8),1,0) -> 1 | ... Z7: =IF(AND(Z5>Constr_Start_Date,Z5<=Constr_P8),1,0) -> 0
C8: Total Operational Turbines: | D8: # | E8: =S8 -> 103 | G8: {=_xlfn.IFS(G5>=Constr_P8,Inputs_Assumptions!$F$92,G5>=Constr_P7,Inputs_Assumptions!$F$91,G5>=Constr_P6,Inputs_Assumptions!$F$90,G5>=Constr_P5,Inputs_Assumptions!$F$89,G5>=Constr_P4,Inputs_Assumptions!$F$88,G5>=Constr_P3,Inputs_Assumptions!$F$87,G5>=Constr_P2,Inputs_Assumptions!$F$86,G5>=Constr_P1,Inputs_Assumptions!$F$85,"TRUE",0)} -> 0 | H8: {=_xlfn.IFS(H5>=Constr_P8,Inputs_Assumptions!$F$92,H5>=Constr_P7,Inputs_Assumptions!$F$91,H5>=Constr_P6,Inputs_Assumptions!$F$90,H5>=Constr_P5,Inputs_Assumptions!$F$89,H5>=Constr_P4,Inputs_Assumptions!$F$88,H5>=Constr_P3,Inputs_Assumptions!$F$87,H5>=Constr_P2,Inputs_Assumptions!$F$86,H5>=Constr_P1,Inputs_Assumptions!$F$85,"TRUE",0)} -> 0 | I8: {=_xlfn.IFS(I5>=Constr_P8,Inputs_Assumptions!$F$92,I5>=Constr_P7,Inputs_Assumptions!$F$91,I5>=Constr_P6,Inputs_Assumptions!$F$90,I5>=Constr_P5,Inputs_Assumptions!$F$89,I5>=Constr_P4,Inputs_Assumptions!$F$88,I5>=Constr_P3,Inputs_Assumptions!$F$87,I5>=Constr_P2,Inputs_Assumptions!$F$86,I5>=Constr_P1,Inputs_Assumptions!$F$85,"TRUE",0)} -> 0 | J8: {=_xlfn.IFS(J5>=Constr_P8,Inputs_Assumptions!$F$92,J5>=Constr_P7,Inputs_Assumptions!$F$91,J5>=Constr_P6,Inputs_Assumptions!$F$90,J5>=Constr_P5,Inputs_Assumptions!$F$89,J5>=Constr_P4,Inputs_Assumptions!$F$88,J5>=Constr_P3,Inputs_Assumptions!$F$87,J5>=Constr_P2,Inputs_Assumptions!$F$86,J5>=Constr_P1,Inputs_Assumptions!$F$85,"TRUE",0)} -> 0 | K8: {=_xlfn.IFS(K5>=Constr_P8,Inputs_Assumptions!$F$92,K5>=Constr_P7,Inputs_Assumptions!$F$91,K5>=Constr_P6,Inputs_Assumptions!$F$90,K5>=Constr_P5,Inputs_Assumptions!$F$89,K5>=Constr_P4,Inputs_Assumptions!$F$88,K5>=Constr_P3,Inputs_Assumptions!$F$87,K5>=Constr_P2,Inputs_Assumptions!$F$86,K5>=Constr_P1,Inputs_Assumptions!$F$85,"TRUE",0)} -> 0 | L8: {=_xlfn.IFS(L5>=Constr_P8,Inputs_Assumptions!$F$92,L5>=Constr_P7,Inputs_Assumptions!$F$91,L5>=Constr_P6,Inputs_Assumptions!$F$90,L5>=Constr_P5,Inputs_Assumptions!$F$89,L5>=Constr_P4,Inputs_Assumptions!$F$88,L5>=Constr_P3,Inputs_Assumptions!$F$87,L5>=Constr_P2,Inputs_Assumptions!$F$86,L5>=Constr_P1,Inputs_Assumptions!$F$85,"TRUE",0)} -> 6 | M8: {=_xlfn.IFS(M5>=Constr_P8,Inputs_Assumptions!$F$92,M5>=Constr_P7,Inputs_Assumptions!$F$91,M5>=Constr_P6,Inputs_Assumptions!$F$90,M5>=Constr_P5,Inputs_Assumptions!$F$89,M5>=Constr_P4,Inputs_Assumptions!$F$88,M5>=Constr_P3,Inputs_Assumptions!$F$87,M5>=Constr_P2,Inputs_Assumptions!$F$86,M5>=Constr_P1,Inputs_Assumptions!$F$85,"TRUE",0)} -> 22 | N8: {=_xlfn.IFS(N5>=Constr_P8,Inputs_Assumptions!$F$92,N5>=Constr_P7,Inputs_Assumptions!$F$91,N5>=Constr_P6,Inputs_Assumptions!$F$90,N5>=Constr_P5,Inputs_Assumptions!$F$89,N5>=Constr_P4,Inputs_Assumptions!$F$88,N5>=Constr_P3,Inputs_Assumptions!$F$87,N5>=Constr_P2,Inputs_Assumptions!$F$86,N5>=Constr_P1,Inputs_Assumptions!$F$85,"TRUE",0)} -> 30 | ... Z8: {=_xlfn.IFS(Z5>=Constr_P8,Inputs_Assumptions!$F$92,Z5>=Constr_P7,Inputs_Assumptions!$F$91,Z5>=Constr_P6,Inputs_Assumptions!$F$90,Z5>=Constr_P5,Inputs_Assumptions!$F$89,Z5>=Constr_P4,Inputs_Assumptions!$F$88,Z5>=Constr_P3,Inputs_Assumptions!$F$87,Z5>=Constr_P2,Inputs_Assumptions!$F$86,Z5>=Constr_P1,Inputs_Assumptions!$F$85,"TRUE",0)} -> 103
C9: Percentage of Construction Capex Costs: | D9: % | E9: =SUM(G9:Z9) -> 1 | G9: =(H8-G8)/$E$8 -> 0 | H9: =(I8-H8)/$E$8 -> 0 | I9: =(J8-I8)/$E$8 -> 0 | J9: =(K8-J8)/$E$8 -> 0 | K9: 0 | L9: =(L8)/$E$8 -> 0.058252427 | M9: =(M8-L8)/$E$8 -> 0.15533981 | N9: =(N8-M8)/$E$8 -> 0.077669903 | O9: =(O8-N8)/$E$8 -> 0.067961165 | P9: =(P8-O8)/$E$8 -> 0.22330097 | Q9: =(Q8-P8)/$E$8 -> 0.24271845 | R9: =(R8-Q8)/$E$8 -> 0.11650485 | S9: =(S8-R8)/$E$8 -> 0.058252427 | T9: =(U8-T8)/$E$8 -> 0 | U9: =(V8-U8)/$E$8 -> 0 | V9: 0 | W9: 0 | X9: 0 | Y9: 0 | Z9: 0
C10: Percentage of Infrastructure Capex Costs: | D10: % | E10: =SUM(G10:Z10) -> 1 | G10: 0 | H10: 0 | I10: =L9 -> 0.058252427 | J10: =M9 -> 0.15533981 | K10: =N9 -> 0.077669903 | L10: =O9 -> 0.067961165 | M10: =P9 -> 0.22330097 | N10: =Q9 -> 0.24271845 | O10: =R9 -> 0.11650485 | P10: =S9 -> 0.058252427 | Q10: =T9 -> 0 | R10: =Q10 -> 0 | S10: =R10 -> 0 | T10: =S10 -> 0 | U10: =T10 -> 0 | V10: =U10 -> 0 | W10: =V10 -> 0 | X10: =W10 -> 0 | Y10: =X10 -> 0 | Z10: =Y10 -> 0
C13: (+) Construction Capex Costs: | D13: £ M | E13: =SUM(G13:Z13) -> 1949.79 | G13: =(Inputs_Assumptions!$E$28*Inputs_Assumptions!$E$108*1000/Million)*G9*Equity_In_Project -> 0 | H13: =(Inputs_Assumptions!$E$28*Inputs_Assumptions!$E$108*1000/Million)*H9*Equity_In_Project -> 0 | I13: =(Inputs_Assumptions!$E$28*Inputs_Assumptions!$E$108*1000/Million)*I9*Equity_In_Project -> 0 | J13: =(Inputs_Assumptions!$E$28*Inputs_Assumptions!$E$108*1000/Million)*J9*Equity_In_Project -> 0 | K13: =(Inputs_Assumptions!$E$28*Inputs_Assumptions!$E$108*1000/Million)*K9*Equity_In_Project -> 0 | L13: =(Inputs_Assumptions!$E$28*Inputs_Assumptions!$E$108*1000/Million)*L9*Equity_In_Project -> 113.58 | M13: =(Inputs_Assumptions!$E$28*Inputs_Assumptions!$E$108*1000/Million)*M9*Equity_In_Project -> 302.88 | N13: =(Inputs_Assumptions!$E$28*Inputs_Assumptions!$E$108*1000/Million)*N9*Equity_In_Project -> 151.44 | ... Z13: =(Inputs_Assumptions!$E$28*Inputs_Assumptions!$E$108*1000/Million)*Z9*Equity_In_Project -> 0
C14: (+) Infrastructure Capex Costs: | D14: £ M | E14: =SUM(G14:Z14) -> 424.875 | G14: =(Inputs_Assumptions!$E$28*Inputs_Assumptions!$E$109*1000/Million)*G10*Equity_In_Project -> 0 | H14: =(Inputs_Assumptions!$E$28*Inputs_Assumptions!$E$109*1000/Million)*H10*Equity_In_Project -> 0 | I14: =(Inputs_Assumptions!$E$28*Inputs_Assumptions!$E$109*1000/Million)*I10*Equity_In_Project -> 24.75 | J14: =(Inputs_Assumptions!$E$28*Inputs_Assumptions!$E$109*1000/Million)*J10*Equity_In_Project -> 66 | K14: =(Inputs_Assumptions!$E$28*Inputs_Assumptions!$E$109*1000/Million)*K10*Equity_In_Project -> 33 | L14: =(Inputs_Assumptions!$E$28*Inputs_Assumptions!$E$109*1000/Million)*L10*Equity_In_Project -> 28.875 | M14: =(Inputs_Assumptions!$E$28*Inputs_Assumptions!$E$109*1000/Million)*M10*Equity_In_Project -> 94.875 | N14: =(Inputs_Assumptions!$E$28*Inputs_Assumptions!$E$109*1000/Million)*N10*Equity_In_Project -> 103.125 | ... Z14: =(Inputs_Assumptions!$E$28*Inputs_Assumptions!$E$109*1000/Million)*Z10*Equity_In_Project -> 0
C15: (+) Contigency Costs: | D15: £ M | E15: =SUM(G15:Z15) -> 59.366625 | G15: =SUM(G13:G14)*Contigency -> 0 | H15: =SUM(H13:H14)*Contigency -> 0 | I15: =SUM(I13:I14)*Contigency -> 0.61875 | J15: =SUM(J13:J14)*Contigency -> 1.65 | K15: =SUM(K13:K14)*Contigency -> 0.825 | L15: =SUM(L13:L14)*Contigency -> 3.561375 | M15: =SUM(M13:M14)*Contigency -> 9.943875 | N15: =SUM(N13:N14)*Contigency -> 6.364125 | ... Z15: =SUM(Z13:Z14)*Contigency -> 0
C16: (+) Debt Service Reserve Account Costs: | D16: £ M | E16: =SUM(G16:Z16) -> 60.613922 | G16: =IF(G5<=Debt_Refinance_Date,IRR_Revenue_Model!G114,0) -> 0 | H16: =IF(H5<=Debt_Refinance_Date,IRR_Revenue_Model!H114,0) -> 0 | I16: =IF(I5<=Debt_Refinance_Date,IRR_Revenue_Model!I114,0) -> 0 | J16: =IF(J5<=Debt_Refinance_Date,IRR_Revenue_Model!J114,0) -> 0 | K16: =IF(K5<=Debt_Refinance_Date,IRR_Revenue_Model!K114,0) -> 0 | L16: =IF(L5<=Debt_Refinance_Date,IRR_Revenue_Model!L114,0) -> 0 | M16: =IF(M5<=Debt_Refinance_Date,IRR_Revenue_Model!M114,0) -> 0 | N16: =IF(N5<=Debt_Refinance_Date,IRR_Revenue_Model!N114,0) -> 0 | ... V16: =IF(V5<=Debt_Refinance_Date,IRR_Revenue_Model!V114,0) -> 30.961047 | W16: =IF(W5<=Debt_Refinance_Date,IRR_Revenue_Model!W114-IRR_Revenue_Model!V114,0) -> 29.652874 | X16: =IF(X5<=Debt_Refinance_Date,IRR_Revenue_Model!X114,0) -> 0 | Y16: =IF(Y5<=Debt_Refinance_Date,IRR_Revenue_Model!Y114,0) -> 0 | Z16: =IF(Z5<=Debt_Refinance_Date,IRR_Revenue_Model!Z114,0) -> 0
C17: Total Construction Capex Costs: | D17: £ M | E17: =SUM(G17:Z17) -> 2494.6455 | G17: =SUM(G13:G16) -> 0 | H17: =SUM(H13:H16) -> 0 | I17: =SUM(I13:I16) -> 25.36875 | J17: =SUM(J13:J16) -> 67.65 | K17: =SUM(K13:K16) -> 33.825 | L17: =SUM(L13:L16) -> 146.01637 | M17: =SUM(M13:M16) -> 407.69887 | N17: =SUM(N13:N16) -> 260.92912 | ... Z17: =SUM(Z13:Z16) -> 0
C19: (+) Interest During Construction (IDC): | D19: £ M | E19: =SUM(G19:Z19) -> 149.30938 | G19: =IF(AND(G5>FID_Date,G5<Debt_Refinance_Date),G31*Inputs_Assumptions!$E$164,0) -> 0 | H19: =IF(AND(H5>FID_Date,H5<Debt_Refinance_Date),H31*Inputs_Assumptions!$E$164,0) -> 0 | I19: =IF(AND(I5>FID_Date,I5<Debt_Refinance_Date),I31*Inputs_Assumptions!$E$164,0) -> 0 | J19: =IF(AND(J5>FID_Date,J5<Debt_Refinance_Date),J31*Inputs_Assumptions!$E$164,0) -> 0.46221678 | K19: =IF(AND(K5>FID_Date,K5<Debt_Refinance_Date),K31*Inputs_Assumptions!$E$164,0) -> 1.1328001 | L19: =IF(AND(L5>FID_Date,L5<Debt_Refinance_Date),L31*Inputs_Assumptions!$E$164,0) -> 1.4938109 | M19: =IF(AND(M5>FID_Date,M5<Debt_Refinance_Date),M31*Inputs_Assumptions!$E$164,0) -> 2.9014864 | N19: =IF(AND(N5>FID_Date,N5<Debt_Refinance_Date),N31*Inputs_Assumptions!$E$164,0) -> 6.7045939 | ... Z19: =IF(AND(Z5>FID_Date,Z5<Debt_Refinance_Date),Z31*Inputs_Assumptions!$E$164,0) -> 0
C20: (+) Upfront Loan Fees: | D20: £ M | E20: =SUM(G20:Z20) -> 20.268995 | G20: =IF(AND(F7<>1,G7=1),Max_Debt_Draw*Loan_Upfront_Fee_Pct,0) -> 0 | H20: =IF(AND(G7<>1,H7=1),Max_Debt_Draw*Loan_Upfront_Fee_Pct,0) -> 0 | I20: =IF(AND(H7<>1,I7=1),Max_Debt_Draw*Loan_Upfront_Fee_Pct,0) -> 20.268995 | J20: =IF(AND(I7<>1,J7=1),Max_Debt_Draw*Loan_Upfront_Fee_Pct,0) -> 0 | K20: =IF(AND(J7<>1,K7=1),Max_Debt_Draw*Loan_Upfront_Fee_Pct,0) -> 0 | L20: =IF(AND(K7<>1,L7=1),Max_Debt_Draw*Loan_Upfront_Fee_Pct,0) -> 0 | M20: =IF(AND(L7<>1,M7=1),Max_Debt_Draw*Loan_Upfront_Fee_Pct,0) -> 0 | N20: =IF(AND(M7<>1,N7=1),Max_Debt_Draw*Loan_Upfront_Fee_Pct,0) -> 0 | ... Z20: =IF(AND(Y7<>1,Z7=1),Max_Debt_Draw*Loan_Upfront_Fee_Pct,0) -> 0
C21: (+) Loan Commitment Fees: | D21: £ M | E21: =SUM(G21:Z21) -> 30.562564 | G21: =IF(AND(G5>FID_Date,G5<Debt_Refinance_Date),G28*Inputs_Assumptions!$E$169,0) -> 0 | H21: =IF(AND(H5>FID_Date,H5<Debt_Refinance_Date),H28*Inputs_Assumptions!$E$169,0) -> 0 | I21: =IF(AND(I5>FID_Date,I5<Debt_Refinance_Date),I28*Inputs_Assumptions!$E$169,0) -> 4.0386853 | J21: =IF(AND(J5>FID_Date,J5<Debt_Refinance_Date),J28*Inputs_Assumptions!$E$169,0) -> 3.9582621 | K21: =IF(AND(K5>FID_Date,K5<Debt_Refinance_Date),K28*Inputs_Assumptions!$E$169,0) -> 3.8415842 | L21: =IF(AND(L5>FID_Date,L5<Debt_Refinance_Date),L28*Inputs_Assumptions!$E$169,0) -> 3.7787703 | M21: =IF(AND(M5>FID_Date,M5<Debt_Refinance_Date),M28*Inputs_Assumptions!$E$169,0) -> 3.5338423 | N21: =IF(AND(N5>FID_Date,N5<Debt_Refinance_Date),N28*Inputs_Assumptions!$E$169,0) -> 2.872122 | ... Z21: =IF(AND(Z5>FID_Date,Z5<Debt_Refinance_Date),Z28*Inputs_Assumptions!$E$169,0) -> 0
C22: Total Construction Costs: | D22: £ M | E22: =SUM(G22:Z22) -> 2694.7865 | G22: =SUM(G13:G16)+SUM(G19:G21) -> 0 | H22: =SUM(H13:H16)+SUM(H19:H21) -> 0 | I22: =SUM(I13:I16)+SUM(I19:I21) -> 49.67643 | J22: =SUM(J13:J16)+SUM(J19:J21) -> 72.070479 | K22: =SUM(K13:K16)+SUM(K19:K21) -> 38.799384 | L22: =SUM(L13:L16)+SUM(L19:L21) -> 151.28896 | M22: =SUM(M13:M16)+SUM(M19:M21) -> 414.1342 | N22: =SUM(N13:N16)+SUM(N19:N21) -> 270.50584 | ... Z22: =SUM(Z13:Z16)+SUM(Z19:Z21) -> 0
C24: Equity Draw: | D24: £ M | E24: =SUM(G24:Z24) -> 921.9604 | G24: =IF(AND(G5>FID_Date,G5<Debt_Refinance_Date),IF(G16>0,(G22-G16)*(1-Constr_Debt_Pct),G22*(1-Constr_Debt_Pct)),0) -> 0 | H24: =IF(AND(H5>FID_Date,H5<Debt_Refinance_Date),IF(H16>0,(H22-H16)*(1-Constr_Debt_Pct),H22*(1-Constr_Debt_Pct)),0) -> 0 | I24: =IF(AND(I5>FID_Date,I5<Debt_Refinance_Date),IF(I16>0,(I22-I16)*(1-Constr_Debt_Pct),I22*(1-Constr_Debt_Pct)),0) -> 17.386751 | J24: =IF(AND(J5>FID_Date,J5<Debt_Refinance_Date),IF(J16>0,(J22-J16)*(1-Constr_Debt_Pct),J22*(1-Constr_Debt_Pct)),0) -> 25.224668 | K24: =IF(AND(K5>FID_Date,K5<Debt_Refinance_Date),IF(K16>0,(K22-K16)*(1-Constr_Debt_Pct),K22*(1-Constr_Debt_Pct)),0) -> 13.579785 | L24: =IF(AND(L5>FID_Date,L5<Debt_Refinance_Date),IF(L16>0,(L22-L16)*(1-Constr_Debt_Pct),L22*(1-Constr_Debt_Pct)),0) -> 52.951135 | M24: =IF(AND(M5>FID_Date,M5<Debt_Refinance_Date),IF(M16>0,(M22-M16)*(1-Constr_Debt_Pct),M22*(1-Constr_Debt_Pct)),0) -> 144.94697 | N24: =IF(AND(N5>FID_Date,N5<Debt_Refinance_Date),IF(N16>0,(N22-N16)*(1-Constr_Debt_Pct),N22*(1-Constr_Debt_Pct)),0) -> 94.677044 | ... Z24: =IF(AND(Z5>FID_Date,Z5<Debt_Refinance_Date),IF(Z16>0,(Z22-Z16)*(1-Constr_Debt_Pct),Z22*(1-Constr_Debt_Pct)),0) -> 0
C25: Construction Loan Draw (Without Repayment during Construction): | D25: £ M | E25: =SUM(G25:Z25) -> 1772.8261 | G25: =G22-G24 -> 0 | H25: =H22-H24 -> 0 | I25: =I22-I24 -> 32.28968 | J25: =J22-J24 -> 46.845811 | K25: =K22-K24 -> 25.2196 | L25: =L22-L24 -> 98.337821 | M25: =M22-M24 -> 269.18723 | N25: =N22-N24 -> 175.8288 | ... Z25: =Z22-Z24 -> 0
C26: Construction Loan Draw (Repayment during Construction): | D26: £ M | E26: =SUM(G26:Z26) -> 1381.2446 | G26: =IF(G5<=Debt_Refinance_Date,G25-IRR_Revenue_Model!G89,0) -> 0 | H26: =IF(H5<=Debt_Refinance_Date,H25-IRR_Revenue_Model!H89,0) -> 0 | I26: =IF(I5<=Debt_Refinance_Date,I25-IRR_Revenue_Model!I89,0) -> 32.28968 | J26: =IF(J5<=Debt_Refinance_Date,J25-IRR_Revenue_Model!J89,0) -> 46.845811 | K26: =IF(K5<=Debt_Refinance_Date,K25-IRR_Revenue_Model!K89,0) -> 25.2196 | L26: =IF(L5<=Debt_Refinance_Date,L25-IRR_Revenue_Model!L89,0) -> 98.337821 | M26: =IF(M5<=Debt_Refinance_Date,M25-IRR_Revenue_Model!M89,0) -> 265.67864 | N26: =IF(N5<=Debt_Refinance_Date,N25-IRR_Revenue_Model!N89,0) -> 160.57438 | ... Z26: =IF(Z5<=Debt_Refinance_Date,Z25-IRR_Revenue_Model!Z89,0) -> 0
C28: Undrawn Loan: | D28: £ M | G28: =IF(AND(G5>Constr_Start_Date,G5<Debt_Refinance_Date),Max_Debt_Draw-G31,0) -> 0 | H28: =IF(AND(H5>Constr_Start_Date,H5<Debt_Refinance_Date),Max_Debt_Draw-H31,0) -> 0 | I28: =IF(AND(I5>Constr_Start_Date,I5<Debt_Refinance_Date),Max_Debt_Draw-I31,0) -> 1621.5196 | J28: =IF(AND(J5>Constr_Start_Date,J5<Debt_Refinance_Date),Max_Debt_Draw-J31,0) -> 1589.2299 | K28: =IF(AND(K5>Constr_Start_Date,K5<Debt_Refinance_Date),Max_Debt_Draw-K31,0) -> 1542.3841 | L28: =IF(AND(L5>Constr_Start_Date,L5<Debt_Refinance_Date),Max_Debt_Draw-L31,0) -> 1517.1645 | M28: =IF(AND(M5>Constr_Start_Date,M5<Debt_Refinance_Date),Max_Debt_Draw-M31,0) -> 1418.8267 | N28: =IF(AND(N5>Constr_Start_Date,N5<Debt_Refinance_Date),Max_Debt_Draw-N31,0) -> 1153.1481 | ... Z28: =IF(AND(Z5>Constr_Start_Date,Z5<Debt_Refinance_Date),Max_Debt_Draw-Z31,0) -> 0
C30: Construction Loan:
C31: Beginning Debt Balance: | D31: £ M | G31: 0 | H31: =G33 -> 0 | I31: =H33 -> 0 | J31: =I33 -> 32.28968 | K31: =J33 -> 79.135491 | L31: =K33 -> 104.35509 | M31: =L33 -> 202.69291 | N31: =M33 -> 468.37155 | O31: =N33 -> 628.94593 | ... Z31: =Y33 -> 1381.2446
C32: (+) Draws: | D32: £ M | G32: =G26 -> 0 | H32: =H26 -> 0 | I32: =I26 -> 32.28968 | J32: =J26 -> 46.845811 | K32: =K26 -> 25.2196 | L32: =L26 -> 98.337821 | M32: =M26 -> 265.67864 | N32: =N26 -> 160.57438 | ... Z32: =Z26 -> 0
C33: Ending Debt Balance: | D33: £ M | G33: =SUM(G31:G32) -> 0 | H33: =SUM(H31:H32) -> 0 | I33: =SUM(I31:I32) -> 32.28968 | J33: =SUM(J31:J32) -> 79.135491 | K33: =SUM(K31:K32) -> 104.35509 | L33: =SUM(L31:L32) -> 202.69291 | M33: =SUM(M31:M32) -> 468.37155 | N33: =SUM(N31:N32) -> 628.94593 | ... Z33: =SUM(Z31:Z32) -> 1381.2446

Sheet IRR_Revenue_Model
B2: Quarterly Financial Model and Cash Flow Projections
G4: Construction & Operation Period (See Flags):
B5: Timelines and Escalation Factors: | D5: =Inputs_Assumptions!$D$4 -> Units: | G5: =DATE(YEAR(Constr_Start_Date),3,31) -> 46112 | H5: =EOMONTH(G5,Months_in_Quarter) -> 46203 | I5: =EOMONTH(H5,Months_in_Quarter) -> 46295 | J5: =EOMONTH(I5,Months_in_Quarter) -> 46387 | K5: =EOMONTH(J5,Months_in_Quarter) -> 46477 | L5: =EOMONTH(K5,Months_in_Quarter) -> 46568 | M5: =EOMONTH(L5,Months_in_Quarter) -> 46660 | N5: =EOMONTH(M5,Months_in_Quarter) -> 46752 | O5: =EOMONTH(N5,Months_in_Quarter) -> 46843 | ... FA5: =EOMONTH(EZ5,Months_in_Quarter) -> 59809
C7: Calendar Year: | D7: Year | G7: =YEAR(G5) -> 2026 | H7: =YEAR(H5) -> 2026 | I7: =YEAR(I5) -> 2026 | J7: =YEAR(J5) -> 2026 | K7: =YEAR(K5) -> 2027 | L7: =YEAR(L5) -> 2027 | M7: =YEAR(M5) -> 2027 | N7: =YEAR(N5) -> 2027 | ... FA7: =YEAR(FA5) -> 2063
C8: New Year: | D8: # | G8: 1 | H8: =IF(AND(ISNUMBER(G7),G7<>H7),1,0) -> 0 | I8: =IF(AND(ISNUMBER(H7),H7<>I7),1,0) -> 0 | J8: =IF(AND(ISNUMBER(I7),I7<>J7),1,0) -> 0 | K8: =IF(AND(ISNUMBER(J7),J7<>K7),1,0) -> 1 | L8: =IF(AND(ISNUMBER(K7),K7<>L7),1,0) -> 0 | M8: =IF(AND(ISNUMBER(L7),L7<>M7),1,0) -> 0 | N8: =IF(AND(ISNUMBER(M7),M7<>N7),1,0) -> 0 | O8: =IF(AND(ISNUMBER(N7),N7<>O7),1,0) -> 1 | ... FA8: =IF(AND(ISNUMBER(EZ7),EZ7<>FA7),1,0) -> 0
C9: Quarter of Calendar Year: | D9: # | G9: 1 | H9: =IF(H8=1,1,G9+1) -> 2 | I9: =IF(I8=1,1,H9+1) -> 3 | J9: =IF(J8=1,1,I9+1) -> 4 | K9: =IF(K8=1,1,J9+1) -> 1 | L9: =IF(L8=1,1,K9+1) -> 2 | M9: =IF(M8=1,1,L9+1) -> 3 | N9: =IF(N8=1,1,M9+1) -> 4 | O9: =IF(O8=1,1,N9+1) -> 1 | ... FA9: =IF(FA8=1,1,EZ9+1) -> 3
C11: Construction Period Flag: | D11: # | E11: =SUM(G11:EI11) -> 11 | G11: =IF(AND(G5>Constr_Start_Date,G5<=Constr_End_Date),1,0) -> 0 | H11: =IF(AND(H5>Constr_Start_Date,H5<=Constr_End_Date),1,0) -> 0 | I11: =IF(AND(I5>Constr_Start_Date,I5<=Constr_End_Date),1,0) -> 1 | J11: =IF(AND(J5>Constr_Start_Date,J5<=Constr_End_Date),1,0) -> 1 | K11: =IF(AND(K5>Constr_Start_Date,K5<=Constr_End_Date),1,0) -> 1 | L11: =IF(AND(L5>Constr_Start_Date,L5<=Constr_End_Date),1,0) -> 1 | M11: =IF(AND(M5>Constr_Start_Date,M5<=Constr_End_Date),1,0) -> 1 | N11: =IF(AND(N5>Constr_Start_Date,N5<=Constr_End_Date),1,0) -> 1 | ... FA11: =IF(AND(FA5>Constr_Start_Date,FA5<=Constr_End_Date),1,0) -> 0
C12: Refinancing Period Flag: | D12: # | E12: =SUM(G12:EI12) -> 1 | G12: =IF(AND(G5>Constr_End_Date,G5=Debt_Refinance_Date),1,0) -> 0 | H12: =IF(AND(H5>Constr_End_Date,H5=Debt_Refinance_Date),1,0) -> 0 | I12: =IF(AND(I5>Constr_End_Date,I5=Debt_Refinance_Date),1,0) -> 0 | J12: =IF(AND(J5>Constr_End_Date,J5=Debt_Refinance_Date),1,0) -> 0 | K12: =IF(AND(K5>Constr_End_Date,K5=Debt_Refinance_Date),1,0) -> 0 | L12: =IF(AND(L5>Constr_End_Date,L5=Debt_Refinance_Date),1,0) -> 0 | M12: =IF(AND(M5>Constr_End_Date,M5=Debt_Refinance_Date),1,0) -> 0 | N12: =IF(AND(N5>Constr_End_Date,N5=Debt_Refinance_Date),1,0) -> 0 | ... FA12: =IF(AND(FA5>Constr_End_Date,FA5=Debt_Refinance_Date),1,0) -> 0
C13: Refinancing Quarter #: | D13: # | E13: =MAX(G13:EI13) -> 17 | F13: 0 | G13: =IF(G12=0,(F13+1)*(1-SUM($G12:G12)),F13+1) -> 1 | H13: =IF(H12=0,(G13+1)*(1-SUM($G12:H12)),G13+1) -> 2 | I13: =IF(I12=0,(H13+1)*(1-SUM($G12:I12)),H13+1) -> 3 | J13: =IF(J12=0,(I13+1)*(1-SUM($G12:J12)),I13+1) -> 4 | K13: =IF(K12=0,(J13+1)*(1-SUM($G12:K12)),J13+1) -> 5 | L13: =IF(L12=0,(K13+1)*(1-SUM($G12:L12)),K13+1) -> 6 | M13: =IF(M12=0,(L13+1)*(1-SUM($G12:M12)),L13+1) -> 7 | N13: =IF(N12=0,(M13+1)*(1-SUM($G12:N12)),M13+1) -> 8 | ... FA13: =IF(FA12=0,(EZ13+1)*(1-SUM($G12:FA12)),EZ13+1) -> 0
C15: Operations Period Flag: | D15: # | E15: =SUM(G15:EI15) -> 127 | G15: =IF(AND(G5>Op_Start_Date,G5<=Op_End_Date),1,0) -> 0 | H15: =IF(AND(H5>Op_Start_Date,H5<=Op_End_Date),1,0) -> 0 | I15: =IF(AND(I5>Op_Start_Date,I5<=Op_End_Date),1,0) -> 0 | J15: =IF(AND(J5>Op_Start_Date,J5<=Op_End_Date),1,0) -> 0 | K15: =IF(AND(K5>Op_Start_Date,K5<=Op_End_Date),1,0) -> 0 | L15: =IF(AND(L5>Op_Start_Date,L5<=Op_End_Date),1,0) -> 0 | M15: =IF(AND(M5>Op_Start_Date,M5<=Op_End_Date),1,0) -> 1 | N15: =IF(AND(N5>Op_Start_Date,N5<=Op_End_Date),1,0) -> 1 | ... FA15: =IF(AND(FA5>Op_Start_Date,FA5<=Op_End_Date),1,0) -> 0
C16: Operational Turbine Count: | D16: # | E16: =MAX(G16:EI16) -> 103 | G16: =IF(G11=1,Constr_Phase_Model!G8,F16*G15) -> 0 | H16: =IF(H11=1,Constr_Phase_Model!H8,G16*H15) -> 0 | I16: =IF(I11=1,Constr_Phase_Model!I8,H16*I15) -> 0 | J16: =IF(J11=1,Constr_Phase_Model!J8,I16*J15) -> 0 | K16: =IF(K11=1,Constr_Phase_Model!K8,J16*K15) -> 0 | L16: =IF(L11=1,Constr_Phase_Model!L8,K16*L15) -> 6 | M16: =IF(M11=1,Constr_Phase_Model!M8,L16*M15) -> 22 | N16: =IF(N11=1,Constr_Phase_Model!N8,M16*N15) -> 30 | ... FA16: =IF(FA11=1,Constr_Phase_Model!FA8,EZ16*FA15) -> 0
C17: Electricity Generation Flag: | D17: # | E17: =SUM(G17:EI17) -> 127 | G17: =IF(AND(G5>Op_Start_Date,G5<=Op_End_Date),1,0) -> 0 | H17: =IF(AND(H5>Op_Start_Date,H5<=Op_End_Date),1,0) -> 0 | I17: =IF(AND(I5>Op_Start_Date,I5<=Op_End_Date),1,0) -> 0 | J17: =IF(AND(J5>Op_Start_Date,J5<=Op_End_Date),1,0) -> 0 | K17: =IF(AND(K5>Op_Start_Date,K5<=Op_End_Date),1,0) -> 0 | L17: =IF(AND(L5>Op_Start_Date,L5<=Op_End_Date),1,0) -> 0 | M17: =IF(AND(M5>Op_Start_Date,M5<=Op_End_Date),1,0) -> 1 | N17: =IF(AND(N5>Op_Start_Date,N5<=Op_End_Date),1,0) -> 1 | ... FA17: =IF(AND(FA5>Op_Start_Date,FA5<=Op_End_Date),1,0) -> 0
C18: Electricity Generation Quarter #: | D18: # | G18: {=SUM($G17:G17*G17)} -> 0 | H18: {=SUM($G17:H17*H17)} -> 0 | I18: {=SUM($G17:I17*I17)} -> 0 | J18: {=SUM($G17:J17*J17)} -> 0 | K18: {=SUM($G17:K17*K17)} -> 0 | L18: {=SUM($G17:L17*L17)} -> 0 | M18: {=SUM($G17:M17*M17)} -> 1 | N18: {=SUM($G17:N17*N17)} -> 2 | ... FA18: {=SUM($G17:FA17*FA17)} -> 0
C20: Electricity Rate Escalation Factor: | D20: # | F20: 1 | G20: =((1+Electr_Rate_Escalation)^(1/Quarters_in_Year))*F20 -> 1.0061922 | H20: =((1+Electr_Rate_Escalation)^(1/Quarters_in_Year))*G20 -> 1.0124228 | I20: =((1+Electr_Rate_Escalation)^(1/Quarters_in_Year))*H20 -> 1.018692 | J20: =((1+Electr_Rate_Escalation)^(1/Quarters_in_Year))*I20 -> 1.025 | K20: =((1+Electr_Rate_Escalation)^(1/Quarters_in_Year))*J20 -> 1.0313471 | L20: =((1+Electr_Rate_Escalation)^(1/Quarters_in_Year))*K20 -> 1.0377334 | M20: =((1+Electr_Rate_Escalation)^(1/Quarters_in_Year))*L20 -> 1.0441593 | N20: =((1+Electr_Rate_Escalation)^(1/Quarters_in_Year))*M20 -> 1.050625 | ... FA20: =((1+Electr_Rate_Escalation)^(1/Quarters_in_Year))*EZ20 -> 2.5399544
C21: CPI Cost Escalation Factor: | D21: # | F21: 1 | G21: =((1+CPI_Escalation)^(1/Quarters_in_Year))*F21 -> 1.0061922 | H21: =((1+CPI_Escalation)^(1/Quarters_in_Year))*G21 -> 1.0124228 | I21: =((1+CPI_Escalation)^(1/Quarters_in_Year))*H21 -> 1.018692 | J21: =((1+CPI_Escalation)^(1/Quarters_in_Year))*I21 -> 1.025 | K21: =((1+CPI_Escalation)^(1/Quarters_in_Year))*J21 -> 1.0313471 | L21: =((1+CPI_Escalation)^(1/Quarters_in_Year))*K21 -> 1.0377334 | M21: =((1+CPI_Escalation)^(1/Quarters_in_Year))*L21 -> 1.0441593 | N21: =((1+CPI_Escalation)^(1/Quarters_in_Year))*M21 -> 1.050625 | ... FA21: =((1+CPI_Escalation)^(1/Quarters_in_Year))*EZ21 -> 2.5399544
C22: RPI Cost Escalation Factor: | D22: # | F22: 1 | G22: =((1+RPI_Escalation)^(1/Quarters_in_Year))*F22 -> 1.0070501 | H22: =((1+RPI_Escalation)^(1/Quarters_in_Year))*G22 -> 1.0141499 | I22: =((1+RPI_Escalation)^(1/Quarters_in_Year))*H22 -> 1.0212997 | J22: =((1+RPI_Escalation)^(1/Quarters_in_Year))*I22 -> 1.0285 | K22: =((1+RPI_Escalation)^(1/Quarters_in_Year))*J22 -> 1.035751 | L22: =((1+RPI_Escalation)^(1/Quarters_in_Year))*K22 -> 1.0430532 | M22: =((1+RPI_Escalation)^(1/Quarters_in_Year))*L22 -> 1.0504068 | N22: =((1+RPI_Escalation)^(1/Quarters_in_Year))*M22 -> 1.0578122 | ... FA22: =((1+RPI_Escalation)^(1/Quarters_in_Year))*EZ22 -> 2.8887647
C23: Cumulative Degradation Factor: | D23: # | G23: =IF(AND(G17=1,G16=103),((1-Degradation_Factor)^(1/4))*F23,100%) -> 1 | H23: =IF(H5>Op_End_Date,0%,IF(AND(H17=1, H16=103),((1-Degradation_Factor)^(1/4))*G23,100%)) -> 1 | I23: =IF(I5>Op_End_Date,0%,IF(AND(I17=1, I16=103),((1-Degradation_Factor)^(1/4))*H23,100%)) -> 1 | J23: =IF(J5>Op_End_Date,0%,IF(AND(J17=1, J16=103),((1-Degradation_Factor)^(1/4))*I23,100%)) -> 1 | K23: =IF(K5>Op_End_Date,0%,IF(AND(K17=1, K16=103),((1-Degradation_Factor)^(1/4))*J23,100%)) -> 1 | L23: =IF(L5>Op_End_Date,0%,IF(AND(L17=1, L16=103),((1-Degradation_Factor)^(1/4))*K23,100%)) -> 1 | M23: =IF(M5>Op_End_Date,0%,IF(AND(M17=1, M16=103),((1-Degradation_Factor)^(1/4))*L23,100%)) -> 1 | N23: =IF(N5>Op_End_Date,0%,IF(AND(N17=1, N16=103),((1-Degradation_Factor)^(1/4))*M23,100%)) -> 1 | O23: =IF(O5>Op_End_Date,0%,IF(AND(O17=1, O16=103),((1-Degradation_Factor)^(1/4))*N23,100%)) -> 1 | ... FA23: =IF(FA5>Op_End_Date,0%,IF(AND(FA17=1, FA16=103),((1-Degradation_Factor)^(1/4))*EZ23,100%)) -> 0
C25: Operating Assumptions:
C26: Quarterly Load Factor: | D26: % | G26: {=_xlfn.IFS(G9=1,Inputs_Assumptions!$E$53,G9=2,Inputs_Assumptions!$E$54,G9=3,Inputs_Assumptions!$E$55,G9=4,Inputs_Assumptions!$E$56,"TRUE",0)} -> 0.30207009 | H26: {=_xlfn.IFS(H9=1,Inputs_Assumptions!$E$53,H9=2,Inputs_Assumptions!$E$54,H9=3,Inputs_Assumptions!$E$55,H9=4,Inputs_Assumptions!$E$56,"TRUE",0)} -> 0.19160291 | I26: {=_xlfn.IFS(I9=1,Inputs_Assumptions!$E$53,I9=2,Inputs_Assumptions!$E$54,I9=3,Inputs_Assumptions!$E$55,I9=4,Inputs_Assumptions!$E$56,"TRUE",0)} -> 0.19498704 | J26: {=_xlfn.IFS(J9=1,Inputs_Assumptions!$E$53,J9=2,Inputs_Assumptions!$E$54,J9=3,Inputs_Assumptions!$E$55,J9=4,Inputs_Assumptions!$E$56,"TRUE",0)} -> 0.31133996 | K26: {=_xlfn.IFS(K9=1,Inputs_Assumptions!$E$53,K9=2,Inputs_Assumptions!$E$54,K9=3,Inputs_Assumptions!$E$55,K9=4,Inputs_Assumptions!$E$56,"TRUE",0)} -> 0.30207009 | L26: {=_xlfn.IFS(L9=1,Inputs_Assumptions!$E$53,L9=2,Inputs_Assumptions!$E$54,L9=3,Inputs_Assumptions!$E$55,L9=4,Inputs_Assumptions!$E$56,"TRUE",0)} -> 0.19160291 | M26: {=_xlfn.IFS(M9=1,Inputs_Assumptions!$E$53,M9=2,Inputs_Assumptions!$E$54,M9=3,Inputs_Assumptions!$E$55,M9=4,Inputs_Assumptions!$E$56,"TRUE",0)} -> 0.19498704 | N26: {=_xlfn.IFS(N9=1,Inputs_Assumptions!$E$53,N9=2,Inputs_Assumptions!$E$54,N9=3,Inputs_Assumptions!$E$55,N9=4,Inputs_Assumptions!$E$56,"TRUE",0)} -> 0.31133996 | ... FA26: {=_xlfn.IFS(FA9=1,Inputs_Assumptions!$E$53,FA9=2,Inputs_Assumptions!$E$54,FA9=3,Inputs_Assumptions!$E$55,FA9=4,Inputs_Assumptions!$E$56,"TRUE",0)} -> 0.19498704
C27: Curtailment: | D27: % | G27: {=_xlfn.IFS(G5<Inputs_Assumptions!$E$72,Inputs_Assumptions!$E$69,G5<Inputs_Assumptions!$E$73,Inputs_Assumptions!$E$70,G5<Inputs_Assumptions!$E$74,Inputs_Assumptions!$E$71,"TRUE",0)} -> 0.0035 | H27: {=_xlfn.IFS(H5<Inputs_Assumptions!$E$72,Inputs_Assumptions!$E$69,H5<Inputs_Assumptions!$E$73,Inputs_Assumptions!$E$70,H5<Inputs_Assumptions!$E$74,Inputs_Assumptions!$E$71,"TRUE",0)} -> 0.0035 | I27: {=_xlfn.IFS(I5<Inputs_Assumptions!$E$72,Inputs_Assumptions!$E$69,I5<Inputs_Assumptions!$E$73,Inputs_Assumptions!$E$70,I5<Inputs_Assumptions!$E$74,Inputs_Assumptions!$E$71,"TRUE",0)} -> 0.0035 | J27: {=_xlfn.IFS(J5<Inputs_Assumptions!$E$72,Inputs_Assumptions!$E$69,J5<Inputs_Assumptions!$E$73,Inputs_Assumptions!$E$70,J5<Inputs_Assumptions!$E$74,Inputs_Assumptions!$E$71,"TRUE",0)} -> 0.0035 | K27: {=_xlfn.IFS(K5<Inputs_Assumptions!$E$72,Inputs_Assumptions!$E$69,K5<Inputs_Assumptions!$E$73,Inputs_Assumptions!$E$70,K5<Inputs_Assumptions!$E$74,Inputs_Assumptions!$E$71,"TRUE",0)} -> 0.0035 | L27: {=_xlfn.IFS(L5<Inputs_Assumptions!$E$72,Inputs_Assumptions!$E$69,L5<Inputs_Assumptions!$E$73,Inputs_Assumptions!$E$70,L5<Inputs_Assumptions!$E$74,Inputs_Assumptions!$E$71,"TRUE",0)} -> 0.0035 | M27: {=_xlfn.IFS(M5<Inputs_Assumptions!$E$72,Inputs_Assumptions!$E$69,M5<Inputs_Assumptions!$E$73,Inputs_Assumptions!$E$70,M5<Inputs_Assumptions!$E$74,Inputs_Assumptions!$E$71,"TRUE",0)} -> 0.0035 | N27: {=_xlfn.IFS(N5<Inputs_Assumptions!$E$72,Inputs_Assumptions!$E$69,N5<Inputs_Assumptions!$E$73,Inputs_Assumptions!$E$70,N5<Inputs_Assumptions!$E$74,Inputs_Assumptions!$E$71,"TRUE",0)} -> 0.0035 | ... FA27: {=_xlfn.IFS(FA5<Inputs_Assumptions!$E$72,Inputs_Assumptions!$E$69,FA5<Inputs_Assumptions!$E$73,Inputs_Assumptions!$E$70,FA5<Inputs_Assumptions!$E$74,Inputs_Assumptions!$E$71,"TRUE",0)} -> 0.015
C28: Annual Revenue Loss: | D28: % | G28: {=_xlfn.IFS(G5<Inputs_Assumptions!$E$63,Inputs_Assumptions!$E$58,G5<Inputs_Assumptions!$E$64,Inputs_Assumptions!$E$59,G5<Inputs_Assumptions!$E$65,Inputs_Assumptions!$E$60,G5<Inputs_Assumptions!$E$66,Inputs_Assumptions!$E$61,G5<Inputs_Assumptions!$E$74,Inputs_Assumptions!$E$62,"TRUE",0)} -> 0.025 | H28: {=_xlfn.IFS(H5<Inputs_Assumptions!$E$63,Inputs_Assumptions!$E$58,H5<Inputs_Assumptions!$E$64,Inputs_Assumptions!$E$59,H5<Inputs_Assumptions!$E$65,Inputs_Assumptions!$E$60,H5<Inputs_Assumptions!$E$66,Inputs_Assumptions!$E$61,H5<Inputs_Assumptions!$E$74,Inputs_Assumptions!$E$62,"TRUE",0)} -> 0.025 | I28: {=_xlfn.IFS(I5<Inputs_Assumptions!$E$63,Inputs_Assumptions!$E$58,I5<Inputs_Assumptions!$E$64,Inputs_Assumptions!$E$59,I5<Inputs_Assumptions!$E$65,Inputs_Assumptions!$E$60,I5<Inputs_Assumptions!$E$66,Inputs_Assumptions!$E$61,I5<Inputs_Assumptions!$E$74,Inputs_Assumptions!$E$62,"TRUE",0)} -> 0.025 | J28: {=_xlfn.IFS(J5<Inputs_Assumptions!$E$63,Inputs_Assumptions!$E$58,J5<Inputs_Assumptions!$E$64,Inputs_Assumptions!$E$59,J5<Inputs_Assumptions!$E$65,Inputs_Assumptions!$E$60,J5<Inputs_Assumptions!$E$66,Inputs_Assumptions!$E$61,J5<Inputs_Assumptions!$E$74,Inputs_Assumptions!$E$62,"TRUE",0)} -> 0.025 | K28: {=_xlfn.IFS(K5<Inputs_Assumptions!$E$63,Inputs_Assumptions!$E$58,K5<Inputs_Assumptions!$E$64,Inputs_Assumptions!$E$59,K5<Inputs_Assumptions!$E$65,Inputs_Assumptions!$E$60,K5<Inputs_Assumptions!$E$66,Inputs_Assumptions!$E$61,K5<Inputs_Assumptions!$E$74,Inputs_Assumptions!$E$62,"TRUE",0)} -> 0.025 | L28: {=_xlfn.IFS(L5<Inputs_Assumptions!$E$63,Inputs_Assumptions!$E$58,L5<Inputs_Assumptions!$E$64,Inputs_Assumptions!$E$59,L5<Inputs_Assumptions!$E$65,Inputs_Assumptions!$E$60,L5<Inputs_Assumptions!$E$66,Inputs_Assumptions!$E$61,L5<Inputs_Assumptions!$E$74,Inputs_Assumptions!$E$62,"TRUE",0)} -> 0.025 | M28: {=_xlfn.IFS(M5<Inputs_Assumptions!$E$63,Inputs_Assumptions!$E$58,M5<Inputs_Assumptions!$E$64,Inputs_Assumptions!$E$59,M5<Inputs_Assumptions!$E$65,Inputs_Assumptions!$E$60,M5<Inputs_Assumptions!$E$66,Inputs_Assumptions!$E$61,M5<Inputs_Assumptions!$E$74,Inputs_Assumptions!$E$62,"TRUE",0)} -> 0.025 | N28: {=_xlfn.IFS(N5<Inputs_Assumptions!$E$63,Inputs_Assumptions!$E$58,N5<Inputs_Assumptions!$E$64,Inputs_Assumptions!$E$59,N5<Inputs_Assumptions!$E$65,Inputs_Assumptions!$E$60,N5<Inputs_Assumptions!$E$66,Inputs_Assumptions!$E$61,N5<Inputs_Assumptions!$E$74,Inputs_Assumptions!$E$62,"TRUE",0)} -> 0.025 | ... FA28: {=_xlfn.IFS(FA5<Inputs_Assumptions!$E$63,Inputs_Assumptions!$E$58,FA5<Inputs_Assumptions!$E$64,Inputs_Assumptions!$E$59,FA5<Inputs_Assumptions!$E$65,Inputs_Assumptions!$E$60,FA5<Inputs_Assumptions!$E$66,Inputs_Assumptions!$E$61,FA5<Inputs_Assumptions!$E$74,Inputs_Assumptions!$E$62,"TRUE",0)} -> 0.08
C30: Seasonality Adjusted Net Energy Yield per Turbine: | D30: MWh / Quarter | G30: =G26*Inputs_Assumptions!$E$31 -> 20044.465 | H30: =H26*Inputs_Assumptions!$E$31 -> 12714.194 | I30: =I26*Inputs_Assumptions!$E$31 -> 12938.755 | J30: =J26*Inputs_Assumptions!$E$31 -> 20659.586 | K30: =K26*Inputs_Assumptions!$E$31 -> 20044.465 | L30: =L26*Inputs_Assumptions!$E$31 -> 12714.194 | M30: =M26*Inputs_Assumptions!$E$31 -> 12938.755 | N30: =N26*Inputs_Assumptions!$E$31 -> 20659.586 | ... FA30: =FA26*Inputs_Assumptions!$E$31 -> 12938.755
C31: P-Value Adjusted Net Energy Yield per Turbine: | D31: MWh / Quarter | G31: {=_xlfn.IFS(Inputs_Assumptions!$E$146="P50",Inputs_Assumptions!$E$38*IRR_Revenue_Model!G30,Inputs_Assumptions!$E$146="P75",Inputs_Assumptions!$E$39*IRR_Revenue_Model!G30,Inputs_Assumptions!$E$146="P90",Inputs_Assumptions!$E$40*IRR_Revenue_Model!G30,Inputs_Assumptions!$E$146="P99",Inputs_Assumptions!$E$41*IRR_Revenue_Model!G30,"TRUE",0)} -> 18194.928 | H31: {=_xlfn.IFS(Inputs_Assumptions!$E$146="P50",Inputs_Assumptions!$E$38*IRR_Revenue_Model!H30,Inputs_Assumptions!$E$146="P75",Inputs_Assumptions!$E$39*IRR_Revenue_Model!H30,Inputs_Assumptions!$E$146="P90",Inputs_Assumptions!$E$40*IRR_Revenue_Model!H30,Inputs_Assumptions!$E$146="P99",Inputs_Assumptions!$E$41*IRR_Revenue_Model!H30,"TRUE",0)} -> 11541.034 | I31: {=_xlfn.IFS(Inputs_Assumptions!$E$146="P50",Inputs_Assumptions!$E$38*IRR_Revenue_Model!I30,Inputs_Assumptions!$E$146="P75",Inputs_Assumptions!$E$39*IRR_Revenue_Model!I30,Inputs_Assumptions!$E$146="P90",Inputs_Assumptions!$E$40*IRR_Revenue_Model!I30,Inputs_Assumptions!$E$146="P99",Inputs_Assumptions!$E$41*IRR_Revenue_Model!I30,"TRUE",0)} -> 11744.874 | J31: {=_xlfn.IFS(Inputs_Assumptions!$E$146="P50",Inputs_Assumptions!$E$38*IRR_Revenue_Model!J30,Inputs_Assumptions!$E$146="P75",Inputs_Assumptions!$E$39*IRR_Revenue_Model!J30,Inputs_Assumptions!$E$146="P90",Inputs_Assumptions!$E$40*IRR_Revenue_Model!J30,Inputs_Assumptions!$E$146="P99",Inputs_Assumptions!$E$41*IRR_Revenue_Model!J30,"TRUE",0)} -> 18753.291 | K31: {=_xlfn.IFS(Inputs_Assumptions!$E$146="P50",Inputs_Assumptions!$E$38*IRR_Revenue_Model!K30,Inputs_Assumptions!$E$146="P75",Inputs_Assumptions!$E$39*IRR_Revenue_Model!K30,Inputs_Assumptions!$E$146="P90",Inputs_Assumptions!$E$40*IRR_Revenue_Model!K30,Inputs_Assumptions!$E$146="P99",Inputs_Assumptions!$E$41*IRR_Revenue_Model!K30,"TRUE",0)} -> 18194.928 | L31: {=_xlfn.IFS(Inputs_Assumptions!$E$146="P50",Inputs_Assumptions!$E$38*IRR_Revenue_Model!L30,Inputs_Assumptions!$E$146="P75",Inputs_Assumptions!$E$39*IRR_Revenue_Model!L30,Inputs_Assumptions!$E$146="P90",Inputs_Assumptions!$E$40*IRR_Revenue_Model!L30,Inputs_Assumptions!$E$146="P99",Inputs_Assumptions!$E$41*IRR_Revenue_Model!L30,"TRUE",0)} -> 11541.034 | M31: {=_xlfn.IFS(Inputs_Assumptions!$E$146="P50",Inputs_Assumptions!$E$38*IRR_Revenue_Model!M30,Inputs_Assumptions!$E$146="P75",Inputs_Assumptions!$E$39*IRR_Revenue_Model!M30,Inputs_Assumptions!$E$146="P90",Inputs_Assumptions!$E$40*IRR_Revenue_Model!M30,Inputs_Assumptions!$E$146="P99",Inputs_Assumptions!$E$41*IRR_Revenue_Model!M30,"TRUE",0)} -> 11744.874 | N31: {=_xlfn.IFS(Inputs_Assumptions!$E$146="P50",Inputs_Assumptions!$E$38*IRR_Revenue_Model!N30,Inputs_Assumptions!$E$146="P75",Inputs_Assumptions!$E$39*IRR_Revenue_Model!N30,Inputs_Assumptions!$E$146="P90",Inputs_Assumptions!$E$40*IRR_Revenue_Model!N30,Inputs_Assumptions!$E$146="P99",Inputs_Assumptions!$E$41*IRR_Revenue_Model!N30,"TRUE",0)} -> 18753.291 | ... FA31: {=_xlfn.IFS(Inputs_Assumptions!$E$146="P50",Inputs_Assumptions!$E$38*IRR_Revenue_Model!FA30,Inputs_Assumptions!$E$146="P75",Inputs_Assumptions!$E$39*IRR_Revenue_Model!FA30,Inputs_Assumptions!$E$146="P90",Inputs_Assumptions!$E$40*IRR_Revenue_Model!FA30,Inputs_Assumptions!$E$146="P99",Inputs_Assumptions!$E$41*IRR_Revenue_Model!FA30,"TRUE",0)} -> 11744.874
C32: Degradation Adjusted Net Energy Yield per Turbine: | D32: MWh / Quarter | G32: =G31*G23 -> 18194.928 | H32: =H31*H23 -> 11541.034 | I32: =I31*I23 -> 11744.874 | J32: =J31*J23 -> 18753.291 | K32: =K31*K23 -> 18194.928 | L32: =L31*L23 -> 11541.034 | M32: =M31*M23 -> 11744.874 | N32: =N31*N23 -> 18753.291 | ... FA32: =FA31*FA23 -> 0
C33: Curtailment Adjusted Net Energy Yield per Turbine: | D33: MWh / Quarter | G33: =G32*(1-G27) -> 18131.245 | H33: =H32*(1-H27) -> 11500.64 | I33: =I32*(1-I27) -> 11703.767 | J33: =J32*(1-J27) -> 18687.654 | K33: =K32*(1-K27) -> 18131.245 | L33: =L32*(1-L27) -> 11500.64 | M33: =M32*(1-M27) -> 11703.767 | N33: =N32*(1-N27) -> 18687.654 | ... FA33: =FA32*(1-FA27) -> 0
C34: Annual Revenue Loss Adjusted Net Energy Yield per Turbine: | D34: MWh / Quarter | G34: =G33*(1-G28) -> 17677.964 | H34: =H33*(1-H28) -> 11213.124 | I34: =I33*(1-I28) -> 11411.173 | J34: =J33*(1-J28) -> 18220.463 | K34: =K33*(1-K28) -> 17677.964 | L34: =L33*(1-L28) -> 11213.124 | M34: =M33*(1-M28) -> 11411.173 | N34: =N33*(1-N28) -> 18220.463 | ... FA34: =FA33*(1-FA28) -> 0
C36: Total Electricity Generation (All Turbines - Revenue, Route-to-Market Fee): | D36: MWh / Quarter | G36: =G17*G16*G34 -> 0 | H36: =H17*H16*H34 -> 0 | I36: =I17*I16*I34 -> 0 | J36: =J17*J16*J34 -> 0 | K36: =K17*K16*K34 -> 0 | L36: =L17*L16*L34 -> 0 | M36: =M17*M16*M34 -> 251045.8 | N36: =N17*N16*N34 -> 546613.88 | ... FA36: =FA17*FA16*FA34 -> 0
C37: Total Electricity Generation (All Turbines - Insurance, O&M, Connection and UoS, Seabed): | D37: MW / Quarter | G37: =G16*G17*Inputs_Assumptions!$E$26 -> 0 | H37: =H16*H17*Inputs_Assumptions!$E$26 -> 0 | I37: =I16*I17*Inputs_Assumptions!$E$26 -> 0 | J37: =J16*J17*Inputs_Assumptions!$E$26 -> 0 | K37: =K16*K17*Inputs_Assumptions!$E$26 -> 0 | L37: =L16*L17*Inputs_Assumptions!$E$26 -> 0 | M37: =M16*M17*Inputs_Assumptions!$E$26 -> 330 | N37: =N16*N17*Inputs_Assumptions!$E$26 -> 450 | ... FA37: =FA16*FA17*Inputs_Assumptions!$E$26 -> 0
C39: Escalated Electricity Rate CfD: | D39: £ / MWh | G39: =G20*CfD_Strike_Price -> 94.701204 | H39: =H20*CfD_Strike_Price -> 95.287618 | I39: =I20*CfD_Strike_Price -> 95.877662 | J39: =J20*CfD_Strike_Price -> 96.47136 | K39: =K20*CfD_Strike_Price -> 97.068734 | L39: =L20*CfD_Strike_Price -> 97.669808 | M39: =M20*CfD_Strike_Price -> 98.274603 | N39: =N20*CfD_Strike_Price -> 98.883144 | ... FA39: =FA20*CfD_Strike_Price -> 239.05644
C40: Escalated Electricity Rate Merchant Market: | D40: £ / MWh | G40: =G20*Merchant_Price*(1-Inputs_Assumptions!$E$121) -> 46.526329 | H40: =H20*Merchant_Price*(1-Inputs_Assumptions!$E$121) -> 46.814432 | I40: =I20*Merchant_Price*(1-Inputs_Assumptions!$E$121) -> 47.104318 | J40: =J20*Merchant_Price*(1-Inputs_Assumptions!$E$121) -> 47.396 | K40: =K20*Merchant_Price*(1-Inputs_Assumptions!$E$121) -> 47.689488 | L40: =L20*Merchant_Price*(1-Inputs_Assumptions!$E$121) -> 47.984793 | M40: =M20*Merchant_Price*(1-Inputs_Assumptions!$E$121) -> 48.281926 | N40: =N20*Merchant_Price*(1-Inputs_Assumptions!$E$121) -> 48.5809 | ... FA40: =FA20*Merchant_Price*(1-Inputs_Assumptions!$E$121) -> 117.44749
C42: Escalated Insurance Cost: | D42: £ / MW / Quarter | G42: =(Inputs_Assumptions!$E$112/Quarters_in_Year)*IRR_Revenue_Model!G21*Units -> 2465.171 | H42: =(Inputs_Assumptions!$E$112/Quarters_in_Year)*IRR_Revenue_Model!H21*Units -> 2480.4359 | I42: =(Inputs_Assumptions!$E$112/Quarters_in_Year)*IRR_Revenue_Model!I21*Units -> 2495.7954 | J42: =(Inputs_Assumptions!$E$112/Quarters_in_Year)*IRR_Revenue_Model!J21*Units -> 2511.25 | K42: =(Inputs_Assumptions!$E$112/Quarters_in_Year)*IRR_Revenue_Model!K21*Units -> 2526.8003 | L42: =(Inputs_Assumptions!$E$112/Quarters_in_Year)*IRR_Revenue_Model!L21*Units -> 2542.4468 | M42: =(Inputs_Assumptions!$E$112/Quarters_in_Year)*IRR_Revenue_Model!M21*Units -> 2558.1903 | N42: =(Inputs_Assumptions!$E$112/Quarters_in_Year)*IRR_Revenue_Model!N21*Units -> 2574.0313 | ... FA42: =(Inputs_Assumptions!$E$112/Quarters_in_Year)*IRR_Revenue_Model!FA21*Units -> 6222.8883
C43: Escalated Connection and UoS Charges Cost: | D43: £ / MW / Quarter | G43: =(Inputs_Assumptions!$E$113/Quarters_in_Year)*G22*Units -> 18126.902 | H43: =(Inputs_Assumptions!$E$113/Quarters_in_Year)*H22*Units -> 18254.698 | I43: =(Inputs_Assumptions!$E$113/Quarters_in_Year)*I22*Units -> 18383.395 | J43: =(Inputs_Assumptions!$E$113/Quarters_in_Year)*J22*Units -> 18513 | K43: =(Inputs_Assumptions!$E$113/Quarters_in_Year)*K22*Units -> 18643.518 | L43: =(Inputs_Assumptions!$E$113/Quarters_in_Year)*L22*Units -> 18774.957 | M43: =(Inputs_Assumptions!$E$113/Quarters_in_Year)*M22*Units -> 18907.322 | N43: =(Inputs_Assumptions!$E$113/Quarters_in_Year)*N22*Units -> 19040.62 | ... FA43: =(Inputs_Assumptions!$E$113/Quarters_in_Year)*FA22*Units -> 51997.765
C44: Escalated O&M Cost: | D44: £ / MW / Quarter | G44: =(Inputs_Assumptions!$E$114/Quarters_in_Year)*G21*Units -> 10313.471 | H44: =(Inputs_Assumptions!$E$114/Quarters_in_Year)*H21*Units -> 10377.334 | I44: =(Inputs_Assumptions!$E$114/Quarters_in_Year)*I21*Units -> 10441.593 | J44: =(Inputs_Assumptions!$E$114/Quarters_in_Year)*J21*Units -> 10506.25 | K44: =(Inputs_Assumptions!$E$114/Quarters_in_Year)*K21*Units -> 10571.307 | L44: =(Inputs_Assumptions!$E$114/Quarters_in_Year)*L21*Units -> 10636.767 | M44: =(Inputs_Assumptions!$E$114/Quarters_in_Year)*M21*Units -> 10702.633 | N44: =(Inputs_Assumptions!$E$114/Quarters_in_Year)*N21*Units -> 10768.906 | ... FA44: =(Inputs_Assumptions!$E$114/Quarters_in_Year)*FA21*Units -> 26034.533
C45: Escalated Seabed Lease Cost: | D45: £ / MW / Quarter | G45: =(Inputs_Assumptions!$E$115/Quarters_in_Year)*G22*Units -> 1007.0501 | H45: =(Inputs_Assumptions!$E$115/Quarters_in_Year)*H22*Units -> 1014.1499 | I45: =(Inputs_Assumptions!$E$115/Quarters_in_Year)*I22*Units -> 1021.2997 | J45: =(Inputs_Assumptions!$E$115/Quarters_in_Year)*J22*Units -> 1028.5 | K45: =(Inputs_Assumptions!$E$115/Quarters_in_Year)*K22*Units -> 1035.751 | L45: =(Inputs_Assumptions!$E$115/Quarters_in_Year)*L22*Units -> 1043.0532 | M45: =(Inputs_Assumptions!$E$115/Quarters_in_Year)*M22*Units -> 1050.4068 | N45: =(Inputs_Assumptions!$E$115/Quarters_in_Year)*N22*Units -> 1057.8122 | ... FA45: =(Inputs_Assumptions!$E$115/Quarters_in_Year)*FA22*Units -> 2888.7647
C46: Escalated Route to Market Fee: | D46: £ / MWh | G46: =Inputs_Assumptions!$E$116*IRR_Revenue_Model!G21 -> 2.0123845 | H46: =Inputs_Assumptions!$E$116*IRR_Revenue_Model!H21 -> 2.0248457 | I46: =Inputs_Assumptions!$E$116*IRR_Revenue_Model!I21 -> 2.037384 | J46: =Inputs_Assumptions!$E$116*IRR_Revenue_Model!J21 -> 2.05 | K46: =Inputs_Assumptions!$E$116*IRR_Revenue_Model!K21 -> 2.0626941 | L46: =Inputs_Assumptions!$E$116*IRR_Revenue_Model!L21 -> 2.0754668 | M46: =Inputs_Assumptions!$E$116*IRR_Revenue_Model!M21 -> 2.0883186 | N46: =Inputs_Assumptions!$E$116*IRR_Revenue_Model!N21 -> 2.10125 | ... FA46: =Inputs_Assumptions!$E$116*IRR_Revenue_Model!FA21 -> 5.0799088
C48: Major Maintenance Reserve Account: | D48: £M/Quarter | G48: =(Inputs_Assumptions!$E$192/Quarters_in_Year)*G21 -> 2.5154806 | H48: =(Inputs_Assumptions!$E$192/Quarters_in_Year)*H21 -> 2.5310571 | I48: =(Inputs_Assumptions!$E$192/Quarters_in_Year)*I21 -> 2.54673 | J48: =(Inputs_Assumptions!$E$192/Quarters_in_Year)*J21 -> 2.5625 | K48: =(Inputs_Assumptions!$E$192/Quarters_in_Year)*K21 -> 2.5783676 | L48: =(Inputs_Assumptions!$E$192/Quarters_in_Year)*L21 -> 2.5943335 | M48: =(Inputs_Assumptions!$E$192/Quarters_in_Year)*M21 -> 2.6103983 | N48: =(Inputs_Assumptions!$E$192/Quarters_in_Year)*N21 -> 2.6265625 | ... FA48: =(Inputs_Assumptions!$E$192/Quarters_in_Year)*FA21 -> 6.349886
C49: Decommissioning Security: | D49: £M/Quarter | G49: =(Inputs_Assumptions!$E$193/Quarters_in_Year)*G21 -> 7.5464418 | H49: =(Inputs_Assumptions!$E$193/Quarters_in_Year)*H21 -> 7.5931713 | I49: =(Inputs_Assumptions!$E$193/Quarters_in_Year)*I21 -> 7.6401901 | J49: =(Inputs_Assumptions!$E$193/Quarters_in_Year)*J21 -> 7.6875 | K49: =(Inputs_Assumptions!$E$193/Quarters_in_Year)*K21 -> 7.7351029 | L49: =(Inputs_Assumptions!$E$193/Quarters_in_Year)*L21 -> 7.7830006 | M49: =(Inputs_Assumptions!$E$193/Quarters_in_Year)*M21 -> 7.8311948 | N49: =(Inputs_Assumptions!$E$193/Quarters_in_Year)*N21 -> 7.8796875 | ... FA49: =(Inputs_Assumptions!$E$193/Quarters_in_Year)*FA21 -> 19.049658
C51: Capex per Quarter: | D51: £M | E51: =SUM(G51:FA51) -> 2434.0316 | G51: =IF(G5<=Constr_End_Date,Constr_Phase_Model!G17,0) -> 0 | H51: =IF(H5<=Constr_End_Date,Constr_Phase_Model!H17,0) -> 0 | I51: =IF(I5<=Constr_End_Date,Constr_Phase_Model!I17,0) -> 25.36875 | J51: =IF(J5<=Constr_End_Date,Constr_Phase_Model!J17,0) -> 67.65 | K51: =IF(K5<=Constr_End_Date,Constr_Phase_Model!K17,0) -> 33.825 | L51: =IF(L5<=Constr_End_Date,Constr_Phase_Model!L17,0) -> 146.01637 | M51: =IF(M5<=Constr_End_Date,Constr_Phase_Model!M17,0) -> 407.69887 | N51: =IF(N5<=Constr_End_Date,Constr_Phase_Model!N17,0) -> 260.92912 | ... FA51: =IF(FA5<=Constr_End_Date,Constr_Phase_Model!FA17,0) -> 0
C52: Interest During Construction per Quarter: | D52: £M | E52: =SUM(G52:FA52) -> 149.30938 | G52: =IF(G5<=Debt_Refinance_Date,Constr_Phase_Model!G19,0) -> 0 | H52: =IF(H5<=Debt_Refinance_Date,Constr_Phase_Model!H19,0) -> 0 | I52: =IF(I5<=Debt_Refinance_Date,Constr_Phase_Model!I19,0) -> 0 | J52: =IF(J5<=Debt_Refinance_Date,Constr_Phase_Model!J19,0) -> 0.46221678 | K52: =IF(K5<=Debt_Refinance_Date,Constr_Phase_Model!K19,0) -> 1.1328001 | L52: =IF(L5<=Debt_Refinance_Date,Constr_Phase_Model!L19,0) -> 1.4938109 | M52: =IF(M5<=Debt_Refinance_Date,Constr_Phase_Model!M19,0) -> 2.9014864 | N52: =IF(N5<=Debt_Refinance_Date,Constr_Phase_Model!N19,0) -> 6.7045939 | ... FA52: =IF(FA5<=Debt_Refinance_Date,Constr_Phase_Model!FA19,0) -> 0
C53: Loan Fee per Quarter: | D53: £M | E53: =SUM(G53:FA53) -> 1493.0798 | G53: =IF(AND(G5>=Debt_Refinance_Date,G5<CfD_Expiry_Date),($E$175+$E$176)*Inputs_Assumptions!$E$170,0) -> 0 | H53: =IF(AND(H5>=Debt_Refinance_Date,H5<CfD_Expiry_Date),($E$175+$E$176)*Inputs_Assumptions!$E$170,0) -> 0 | I53: =IF(AND(I5>=Debt_Refinance_Date,I5<CfD_Expiry_Date),($E$175+$E$176)*Inputs_Assumptions!$E$170,0) -> 0 | J53: =IF(AND(J5>=Debt_Refinance_Date,J5<CfD_Expiry_Date),($E$175+$E$176)*Inputs_Assumptions!$E$170,0) -> 0 | K53: =IF(AND(K5>=Debt_Refinance_Date,K5<CfD_Expiry_Date),($E$175+$E$176)*Inputs_Assumptions!$E$170,0) -> 0 | L53: =IF(AND(L5>=Debt_Refinance_Date,L5<CfD_Expiry_Date),($E$175+$E$176)*Inputs_Assumptions!$E$170,0) -> 0 | M53: =IF(AND(M5>=Debt_Refinance_Date,M5<CfD_Expiry_Date),($E$175+$E$176)*Inputs_Assumptions!$E$170,0) -> 0 | N53: =IF(AND(N5>=Debt_Refinance_Date,N5<CfD_Expiry_Date),($E$175+$E$176)*Inputs_Assumptions!$E$170,0) -> 0 | ... FA53: =IF(AND(FA5>=Debt_Refinance_Date,FA5<CfD_Expiry_Date),($E$175+$E$176)*Inputs_Assumptions!$E$170,0) -> 0
G55: =$G$4 -> Construction & Operation Period (See Flags):
B56: Cash Flow Projections: | D56: =D5 -> Units: | G56: =$G$5 -> 46112 | H56: =$H$5 -> 46203 | I56: =$I$5 -> 46295 | J56: =$J$5 -> 46387 | K56: =$K$5 -> 46477 | L56: =$L$5 -> 46568 | M56: =$M$5 -> 46660 | N56: =$N$5 -> 46752 | O56: =$O$5 -> 46843 | P56: =$P$5 -> 46934 | Q56: =$Q$5 -> 47026 | R56: =$R$5 -> 47118 | S56: =$S$5 -> 47208 | T56: =$T$5 -> 47299 | U56: =$U$5 -> 47391 | V56: =$V$5 -> 47483 | W56: =$W$5 -> 47573 | X56: =$X$5 -> 47664 | Y56: =$Y$5 -> 47756 | Z56: =$Z$5 -> 47848 | AA56: =$AA$5 -> 47938 | AB56: =$AB$5 -> 48029 | AC56: =$AC$5 -> 48121 | AD56: =$AD$5 -> 48213 | AE56: =$AE$5 -> 48304 | AF56: =$AF$5 -> 48395 | AG56: =$AG$5 -> 48487 | AH56: =$AH$5 -> 48579 | AI56: =$AI$5 -> 48669 | AJ56: =$AJ$5 -> 48760 | AK56: =$AK$5 -> 48852 | AL56: =$AL$5 -> 48944 | AM56: =$AM$5 -> 49034 | AN56: =$AN$5 -> 49125 | AO56: =$AO$5 -> 49217 | AP56: =$AP$5 -> 49309 | AQ56: =$AQ$5 -> 49399 | AR56: =$AR$5 -> 49490 | AS56: =$AS$5 -> 49582 | AT56: =$AT$5 -> 49674 | AU56: =$AU$5 -> 49765 | AV56: =$AV$5 -> 49856 | AW56: =$AW$5 -> 49948 | AX56: =$AX$5 -> 50040 | AY56: =$AY$5 -> 50130 | AZ56: =$AZ$5 -> 50221 | BA56: =$BA$5 -> 50313 | BB56: =$BB$5 -> 50405 | BC56: =$BC$5 -> 50495 | BD56: =$BD$5 -> 50586 | BE56: =$BE$5 -> 50678 | BF56: =$BF$5 -> 50770 | BG56: =$BG$5 -> 50860 | BH56: =$BH$5 -> 50951 | BI56: =$BI$5 -> 51043 | BJ56: =$BJ$5 -> 51135 | BK56: =$BK$5 -> 51226 | BL56: =$BL$5 -> 51317 | BM56: =$BM$5 -> 51409 | BN56: =$BN$5 -> 51501 | BO56: =$BO$5 -> 51591 | BP56: =$BP$5 -> 51682 | BQ56: =$BQ$5 -> 51774 | BR56: =$BR$5 -> 51866 | BS56: =$BS$5 -> 51956 | BT56: =$BT$5 -> 52047 | BU56: =$BU$5 -> 52139 | BV56: =$BV$5 -> 52231 | BW56: =$BW$5 -> 52321 | BX56: =$BX$5 -> 52412 | BY56: =$BY$5 -> 52504 | BZ56: =$BZ$5 -> 52596 | CA56: =$CA$5 -> 52687 | CB56: =$CB$5 -> 52778 | CC56: =$CC$5 -> 52870 | CD56: =$CD$5 -> 52962 | CE56: =$CE$5 -> 53052 | CF56: =$CF$5 -> 53143 | CG56: =$CG$5 -> 53235 | CH56: =$CH$5 -> 53327 | CI56: =$CI$5 -> 53417 | CJ56: =$CJ$5 -> 53508 | CK56: =$CK$5 -> 53600 | CL56: =$CL$5 -> 53692 | CM56: =$CM$5 -> 53782 | CN56: =$CN$5 -> 53873 | CO56: =$CO$5 -> 53965 | CP56: =$CP$5 -> 54057 | CQ56: =$CQ$5 -> 54148 | CR56: =$CR$5 -> 54239 | CS56: =$CS$5 -> 54331 | CT56: =$CT$5 -> 54423 | CU56: =$CU$5 -> 54513 | CV56: =$CV$5 -> 54604 | CW56: =$CW$5 -> 54696 | CX56: =$CX$5 -> 54788 | CY56: =$CY$5 -> 54878 | CZ56: =$CZ$5 -> 54969 | DA56: =$DA$5 -> 55061 | DB56: =$DB$5 -> 55153 | DC56: =$DC$5 -> 55243 | DD56: =$DD$5 -> 55334 | DE56: =$DE$5 -> 55426 | DF56: =$DF$5 -> 55518 | DG56: =$DG$5 -> 55609 | DH56: =$DH$5 -> 55700 | DI56: =$DI$5 -> 55792 | DJ56: =$DJ$5 -> 55884 | DK56: =$DK$5 -> 55974 | DL56: =$DL$5 -> 56065 | DM56: =$DM$5 -> 56157 | DN56: =$DN$5 -> 56249 | DO56: =$DO$5 -> 56339 | DP56: =$DP$5 -> 56430 | DQ56: =$DQ$5 -> 56522 | DR56: =$DR$5 -> 56614 | DS56: =$DS$5 -> 56704 | DT56: =$DT$5 -> 56795 | DU56: =$DU$5 -> 56887 | DV56: =$DV$5 -> 56979 | DW56: =$DW$5 -> 57070 | DX56: =$DX$5 -> 57161 | DY56: =$DY$5 -> 57253 | DZ56: =$DZ$5 -> 57345 | EA56: =$EA$5 -> 57435 | EB56: =$EB$5 -> 57526 | EC56: =$EC$5 -> 57618 | ED56: =$ED$5 -> 57710 | EE56: =$EE$5 -> 57800 | EF56: =$EF$5 -> 57891 | EG56: =$EG$5 -> 57983 | EH56: =$EH$5 -> 58075 | EI56: =$EI$5 -> 58165 | EJ56: =$EJ$5 -> 58256 | EK56: =$EK$5 -> 58348 | EL56: =$EL$5 -> 58440 | EM56: =$EM$5 -> 58531 | EN56: =$EN$5 -> 58622 | EO56: =$EO$5 -> 58714 | EP56: =$EP$5 -> 58806 | EQ56: =$EQ$5 -> 58896 | ER56: =$ER$5 -> 58987 | ES56: =$ES$5 -> 59079 | ET56: =$ET$5 -> 59171 | EU56: =$EU$5 -> 59261 | EV56: =$EV$5 -> 59352 | EW56: =$EW$5 -> 59444 | EX56: =$EX$5 -> 59536 | EY56: =$EY$5 -> 59626 | EZ56: =$EZ$5 -> 59717 | FA56: =$FA$5 -> 59809
C58: Total Revenue: | D58: £ M | G58: =IF(G56<=CfD_Expiry_Date,G36*IRR_Revenue_Model!G39/Million,G36*IRR_Revenue_Model!G40/Million)*Equity_In_Project -> 0 | H58: =IF(H56<=CfD_Expiry_Date,H36*IRR_Revenue_Model!H39/Million,H36*IRR_Revenue_Model!H40/Million)*Equity_In_Project -> 0 | I58: =IF(I56<=CfD_Expiry_Date,I36*IRR_Revenue_Model!I39/Million,I36*IRR_Revenue_Model!I40/Million)*Equity_In_Project -> 0 | J58: =IF(J56<=CfD_Expiry_Date,J36*IRR_Revenue_Model!J39/Million,J36*IRR_Revenue_Model!J40/Million)*Equity_In_Project -> 0 | K58: =IF(K56<=CfD_Expiry_Date,K36*IRR_Revenue_Model!K39/Million,K36*IRR_Revenue_Model!K40/Million)*Equity_In_Project -> 0 | L58: =IF(L56<=CfD_Expiry_Date,L36*IRR_Revenue_Model!L39/Million,L36*IRR_Revenue_Model!L40/Million)*Equity_In_Project -> 0 | M58: =IF(M56<=CfD_Expiry_Date,M36*IRR_Revenue_Model!M39/Million,M36*IRR_Revenue_Model!M40/Million)*Equity_In_Project -> 12.335713 | N58: =IF(N56<=CfD_Expiry_Date,N36*IRR_Revenue_Model!N39/Million,N36*IRR_Revenue_Model!N40/Million)*Equity_In_Project -> 27.025449 | ... FA58: =IF(FA56<=CfD_Expiry_Date,FA36*IRR_Revenue_Model!FA39/Million,FA36*IRR_Revenue_Model!FA40/Million)*Equity_In_Project -> 0
C59: (-) Insurance Costs: | D59: £ M | G59: =-G37*G42/Million*Equity_In_Project -> 0 | H59: =-H37*H42/Million*Equity_In_Project -> 0 | I59: =-I37*I42/Million*Equity_In_Project -> 0 | J59: =-J37*J42/Million*Equity_In_Project -> 0 | K59: =-K37*K42/Million*Equity_In_Project -> 0 | L59: =-L37*L42/Million*Equity_In_Project -> 0 | M59: =-M37*M42/Million*Equity_In_Project -> -0.4221014 | N59: =-N37*N42/Million*Equity_In_Project -> -0.57915703 | ... FA59: =-FA37*FA42/Million*Equity_In_Project -> 0
C60: (-) Connection and UoS Charges Costs: | D60: £ M | G60: =-G37*G43/Million*Equity_In_Project -> 0 | H60: =-H37*H43/Million*Equity_In_Project -> 0 | I60: =-I37*I43/Million*Equity_In_Project -> 0 | J60: =-J37*J43/Million*Equity_In_Project -> 0 | K60: =-K37*K43/Million*Equity_In_Project -> 0 | L60: =-L37*L43/Million*Equity_In_Project -> 0 | M60: =-M37*M43/Million*Equity_In_Project -> -3.1197081 | N60: =-N37*N43/Million*Equity_In_Project -> -4.2841396 | ... FA60: =-FA37*FA43/Million*Equity_In_Project -> 0
C61: (-) O&M Costs: | D61: £ M | G61: =-G37*G44/Million*Equity_In_Project -> 0 | H61: =-H37*H44/Million*Equity_In_Project -> 0 | I61: =-I37*I44/Million*Equity_In_Project -> 0 | J61: =-J37*J44/Million*Equity_In_Project -> 0 | K61: =-K37*K44/Million*Equity_In_Project -> 0 | L61: =-L37*L44/Million*Equity_In_Project -> 0 | M61: =-M37*M44/Million*Equity_In_Project -> -1.7659344 | N61: =-N37*N44/Million*Equity_In_Project -> -2.4230039 | ... FA61: =-FA37*FA44/Million*Equity_In_Project -> 0
C62: (-) Seabed Lease Costs: | D62: £ M | G62: =-G45*G37/Million*Equity_In_Project -> 0 | H62: =-H45*H37/Million*Equity_In_Project -> 0 | I62: =-I45*I37/Million*Equity_In_Project -> 0 | J62: =-J45*J37/Million*Equity_In_Project -> 0 | K62: =-K45*K37/Million*Equity_In_Project -> 0 | L62: =-L45*L37/Million*Equity_In_Project -> 0 | M62: =-M45*M37/Million*Equity_In_Project -> -0.17331712 | N62: =-N45*N37/Million*Equity_In_Project -> -0.23800776 | ... FA62: =-FA45*FA37/Million*Equity_In_Project -> 0
C63: (-) Route to Market Costs: | D63: £ M | G63: =-G46*G36/Million*Equity_In_Project -> 0 | H63: =-H46*H36/Million*Equity_In_Project -> 0 | I63: =-I46*I36/Million*Equity_In_Project -> 0 | J63: =-J46*J36/Million*Equity_In_Project -> 0 | K63: =-K46*K36/Million*Equity_In_Project -> 0 | L63: =-L46*L36/Million*Equity_In_Project -> 0 | M63: =-M46*M36/Million*Equity_In_Project -> -0.26213181 | N63: =-N46*N36/Million*Equity_In_Project -> -0.57428621 | ... FA63: =-FA46*FA36/Million*Equity_In_Project -> 0
C64: EBITDA: | D64: £ M | G64: =SUM(G58:G63) -> 0 | H64: =SUM(H58:H63) -> 0 | I64: =SUM(I58:I63) -> 0 | J64: =SUM(J58:J63) -> 0 | K64: =SUM(K58:K63) -> 0 | L64: =SUM(L58:L63) -> 0 | M64: =SUM(M58:M63) -> 6.5925203 | N64: =SUM(N58:N63) -> 18.926855 | ... FA64: =SUM(FA58:FA63) -> 0
C65: (-) Depreciation of Initial Construction: | D65: £ M | E65: =SUM(G65:FA65) -> -2079.6439 | G65: =-IF(G17=1,(SUM($G51:G51)+SUM($F65:F65))*Inputs_Assumptions!$E$136,0) -> 0 | H65: =-IF(H17=1,(SUM($G51:H51)+SUM($F65:G65))*Inputs_Assumptions!$E$136,0) -> 0 | I65: =-IF(I17=1,(SUM($G51:I51)+SUM($F65:H65))*Inputs_Assumptions!$E$136,0) -> 0 | J65: =-IF(J17=1,(SUM($G51:J51)+SUM($F65:I65))*Inputs_Assumptions!$E$136,0) -> 0 | K65: =-IF(K17=1,(SUM($G51:K51)+SUM($F65:J65))*Inputs_Assumptions!$E$136,0) -> 0 | L65: =-IF(L17=1,(SUM($G51:L51)+SUM($F65:K65))*Inputs_Assumptions!$E$136,0) -> 0 | M65: =-IF(M17=1,(SUM($G51:M51)+SUM($F65:L65))*Inputs_Assumptions!$E$136,0) -> -10.44646 | N65: =-IF(N17=1,(SUM($G51:N51)+SUM($F65:M65))*Inputs_Assumptions!$E$136,0) -> -14.291325 | ... FA65: =-IF(FA17=1,(SUM($G51:FA51)+SUM($F65:EZ65))*Inputs_Assumptions!$E$136,0) -> 0
C66: (-) Interest During Construction Depreciation: | D66: £ M | E66: =SUM(G66:FA66) -> -126.46601 | G66: =-IF(G17=1,(SUM($G52:G52)+SUM($F66:F66))*Inputs_Assumptions!$E$136,0) -> 0 | H66: =-IF(H17=1,(SUM($G52:H52)+SUM($F66:G66))*Inputs_Assumptions!$E$136,0) -> 0 | I66: =-IF(I17=1,(SUM($G52:I52)+SUM($F66:H66))*Inputs_Assumptions!$E$136,0) -> 0 | J66: =-IF(J17=1,(SUM($G52:J52)+SUM($F66:I66))*Inputs_Assumptions!$E$136,0) -> 0 | K66: =-IF(K17=1,(SUM($G52:K52)+SUM($F66:J66))*Inputs_Assumptions!$E$136,0) -> 0 | L66: =-IF(L17=1,(SUM($G52:L52)+SUM($F66:K66))*Inputs_Assumptions!$E$136,0) -> 0 | M66: =-IF(M17=1,(SUM($G52:M52)+SUM($F66:L66))*Inputs_Assumptions!$E$136,0) -> -0.091950259 | N66: =-IF(N17=1,(SUM($G52:N52)+SUM($F66:M66))*Inputs_Assumptions!$E$136,0) -> -0.19345317 | ... FA66: =-IF(FA17=1,(SUM($G52:FA52)+SUM($F66:EZ66))*Inputs_Assumptions!$E$136,0) -> 0
C67: (-) Upfront Loan Fees Amortisation: | D67: £ M | E67: =SUM(G67:FA67) -> -19.645787 | G67: =-IF(G17=1,G53*Inputs_Assumptions!$E$137/Quarters_in_Year,0) -> 0 | H67: =-IF(H17=1,H53*Inputs_Assumptions!$E$137/Quarters_in_Year,0) -> 0 | I67: =-IF(I17=1,I53*Inputs_Assumptions!$E$137/Quarters_in_Year,0) -> 0 | J67: =-IF(J17=1,J53*Inputs_Assumptions!$E$137/Quarters_in_Year,0) -> 0 | K67: =-IF(K17=1,K53*Inputs_Assumptions!$E$137/Quarters_in_Year,0) -> 0 | L67: =-IF(L17=1,L53*Inputs_Assumptions!$E$137/Quarters_in_Year,0) -> 0 | M67: =-IF(M17=1,M53*Inputs_Assumptions!$E$137/Quarters_in_Year,0) -> 0 | N67: =-IF(N17=1,N53*Inputs_Assumptions!$E$137/Quarters_in_Year,0) -> 0 | ... FA67: =-IF(FA17=1,FA53*Inputs_Assumptions!$E$137/Quarters_in_Year,0) -> 0
C68: (-) Interest Expense: | D68: £ M | E68: =SUM(G68:FA68) -> -1472.4813 | G68: =-G194 -> 0 | H68: =-H194 -> 0 | I68: =-I194 -> 0 | J68: =-J194 -> 0 | K68: =-K194 -> 0 | L68: =-L194 -> 0 | M68: =-M194 -> 0 | N68: =-N194 -> 0 | ... FA68: =-FA194 -> 0
C69: Pre-Tax Income (EBT): | D69: £ M | G69: =SUM(G64:G68) -> 0 | H69: =SUM(H64:H68) -> 0 | I69: =SUM(I64:I68) -> 0 | J69: =SUM(J64:J68) -> 0 | K69: =SUM(K64:K68) -> 0 | L69: =SUM(L64:L68) -> 0 | M69: =SUM(M64:M68) -> -3.94589 | N69: =SUM(N64:N68) -> 4.4420772 | ... FA69: =SUM(FA64:FA68) -> 0
C70: (-) Taxes: | D70: £ M | G70: =-MAX(G69,0)*Tax_Rate -> 0 | H70: =-MAX(H69,0)*Tax_Rate -> 0 | I70: =-MAX(I69,0)*Tax_Rate -> 0 | J70: =-MAX(J69,0)*Tax_Rate -> 0 | K70: =-MAX(K69,0)*Tax_Rate -> 0 | L70: =-MAX(L69,0)*Tax_Rate -> 0 | M70: =-MAX(M69,0)*Tax_Rate -> 0 | N70: =-MAX(N69,0)*Tax_Rate -> -1.1105193 | ... FA70: =-MAX(FA69,0)*Tax_Rate -> 0
C71: Net Income | D71: £ M | G71: =SUM(G69:G70) -> 0 | H71: =SUM(H69:H70) -> 0 | I71: =SUM(I69:I70) -> 0 | J71: =SUM(J69:J70) -> 0 | K71: =SUM(K69:K70) -> 0 | L71: =SUM(L69:L70) -> 0 | M71: =SUM(M69:M70) -> -3.94589 | N71: =SUM(N69:N70) -> 3.3315579 | ... FA71: =SUM(FA69:FA70) -> 0
C73: Beginning NOL Balance: | D73: £ M | G73: =F76 -> 0 | H73: =G76 -> 0 | I73: =H76 -> 0 | J73: =I76 -> 0 | K73: =J76 -> 0 | L73: =K76 -> 0 | M73: =L76 -> 0 | N73: =M76 -> 3.94589 | ... FA73: =EZ76 -> 30.963621
C74: (+) NOLs Created: | D74: £ M | G74: =MAX(-G69,0) -> 0 | H74: =MAX(-H69,0) -> 0 | I74: =MAX(-I69,0) -> 0 | J74: =MAX(-J69,0) -> 0 | K74: =MAX(-K69,0) -> 0 | L74: =MAX(-L69,0) -> 0 | M74: =MAX(-M69,0) -> 3.94589 | N74: =MAX(-N69,0) -> 0 | ... FA74: =MAX(-FA69,0) -> 0
C75: (-) NOLs Used: | D75: £ M | G75: =-MIN(G73+G74,MAX(G69,0)) -> 0 | H75: =-MIN(H73+H74,MAX(H69,0)) -> 0 | I75: =-MIN(I73+I74,MAX(I69,0)) -> 0 | J75: =-MIN(J73+J74,MAX(J69,0)) -> 0 | K75: =-MIN(K73+K74,MAX(K69,0)) -> 0 | L75: =-MIN(L73+L74,MAX(L69,0)) -> 0 | M75: =-MIN(M73+M74,MAX(M69,0)) -> 0 | N75: =-MIN(N73+N74,MAX(N69,0)) -> -3.94589 | ... FA75: =-MIN(FA73+FA74,MAX(FA69,0)) -> 0
C76: Ending NOL Balance: | D76: £ M | F76: 0 | G76: =SUM(G73:G75) -> 0 | H76: =SUM(H73:H75) -> 0 | I76: =SUM(I73:I75) -> 0 | J76: =SUM(J73:J75) -> 0 | K76: =SUM(K73:K75) -> 0 | L76: =SUM(L73:L75) -> 0 | M76: =SUM(M73:M75) -> 3.94589 | N76: =SUM(N73:N75) -> 0 | ... FA76: =SUM(FA73:FA75) -> 30.963621
C78: Cash Flows:
C79: EBITDA | D79: £ M | G79: =G64 -> 0 | H79: =H64 -> 0 | I79: =I64 -> 0 | J79: =J64 -> 0 | K79: =K64 -> 0 | L79: =L64 -> 0 | M79: =M64 -> 6.5925203 | N79: =N64 -> 18.926855 | ... FA79: =FA64 -> 0
C80: (-) Cash Taxes: | D80: £ M | G80: =-MAX(G69+G75,0)*Tax_Rate -> 0 | H80: =-MAX(H69+H75,0)*Tax_Rate -> 0 | I80: =-MAX(I69+I75,0)*Tax_Rate -> 0 | J80: =-MAX(J69+J75,0)*Tax_Rate -> 0 | K80: =-MAX(K69+K75,0)*Tax_Rate -> 0 | L80: =-MAX(L69+L75,0)*Tax_Rate -> 0 | M80: =-MAX(M69+M75,0)*Tax_Rate -> 0 | N80: =-MAX(N69+N75,0)*Tax_Rate -> -0.12404681 | ... FA80: =-MAX(FA69+FA75,0)*Tax_Rate -> 0
C81: (+/-) Change in Working Capital: | D81: £ M | G81: =-(G58-F58)*WC_Pct_Revenue -> 0 | H81: =-(H58-G58)*WC_Pct_Revenue -> 0 | I81: =-(I58-H58)*WC_Pct_Revenue -> 0 | J81: =-(J58-I58)*WC_Pct_Revenue -> 0 | K81: =-(K58-J58)*WC_Pct_Revenue -> 0 | L81: =-(L58-K58)*WC_Pct_Revenue -> 0 | M81: =-(M58-L58)*WC_Pct_Revenue -> -3.0839283 | N81: =-(N58-M58)*WC_Pct_Revenue -> -3.6724341 | ... FA81: =-(FA58-EZ58)*WC_Pct_Revenue -> 0
C82: (-) Maintenance/Decommissioning CapEx: | D82: £ M | G82: =-IF(AND(G15=1,H15=0),Inputs_Assumptions!$E$117*Units*Capacity_per_Turbine*Turbines*G21/Million,0)*Equity_In_Project -> 0 | H82: =-IF(AND(H15=1,I15=0),Inputs_Assumptions!$E$117*Units*Capacity_per_Turbine*Turbines*H21/Million,0)*Equity_In_Project -> 0 | I82: =-IF(AND(I15=1,J15=0),Inputs_Assumptions!$E$117*Units*Capacity_per_Turbine*Turbines*I21/Million,0)*Equity_In_Project -> 0 | J82: =-IF(AND(J15=1,K15=0),Inputs_Assumptions!$E$117*Units*Capacity_per_Turbine*Turbines*J21/Million,0)*Equity_In_Project -> 0 | K82: =-IF(AND(K15=1,L15=0),Inputs_Assumptions!$E$117*Units*Capacity_per_Turbine*Turbines*K21/Million,0)*Equity_In_Project -> 0 | L82: =-IF(AND(L15=1,M15=0),Inputs_Assumptions!$E$117*Units*Capacity_per_Turbine*Turbines*L21/Million,0)*Equity_In_Project -> 0 | M82: =-IF(AND(M15=1,N15=0),Inputs_Assumptions!$E$117*Units*Capacity_per_Turbine*Turbines*M21/Million,0)*Equity_In_Project -> 0 | N82: =-IF(AND(N15=1,O15=0),Inputs_Assumptions!$E$117*Units*Capacity_per_Turbine*Turbines*N21/Million,0)*Equity_In_Project -> 0 | ... FA82: =-IF(AND(FA15=1,FB15=0),Inputs_Assumptions!$E$117*Units*Capacity_per_Turbine*Turbines*FA21/Million,0)*Equity_In_Project -> 0
C83: Cash Flow Available for Debt Service (CFADS Post Tax): | D83: £ M | G83: =SUM(G79:G82) -> 0 | H83: =SUM(H79:H82) -> 0 | I83: =SUM(I79:I82) -> 0 | J83: =SUM(J79:J82) -> 0 | K83: =SUM(K79:K82) -> 0 | L83: =SUM(L79:L82) -> 0 | M83: =SUM(M79:M82) -> 3.508592 | N83: =SUM(N79:N82) -> 15.130374 | ... FA83: =SUM(FA79:FA82) -> 0
C84: (-) Interest Expense: | D84: £ M | G84: =G68 -> 0 | H84: =H68 -> 0 | I84: =I68 -> 0 | J84: =J68 -> 0 | K84: =K68 -> 0 | L84: =L68 -> 0 | M84: =M68 -> 0 | N84: =N68 -> 0 | ... FA84: =FA68 -> 0
C85: (-) Debt Amortization (Sculpted): | D85: £ M | G85: =-G195 -> 0 | H85: =-H195 -> 0 | I85: =-I195 -> 0 | J85: =-J195 -> 0 | K85: =-K195 -> 0 | L85: =-L195 -> 0 | M85: =-M195 -> 0 | N85: =-N195 -> 0 | ... FA85: =-FA195 -> 0
C86: Cash Flow to Equity Investors (exc specific conditions): | D86: £ M | G86: =SUM(G83:G85) -> 0 | H86: =SUM(H83:H85) -> 0 | I86: =SUM(I83:I85) -> 0 | J86: =SUM(J83:J85) -> 0 | K86: =SUM(K83:K85) -> 0 | L86: =SUM(L83:L85) -> 0 | M86: =SUM(M83:M85) -> 3.508592 | N86: =SUM(N83:N85) -> 15.130374 | ... FA86: =SUM(FA83:FA85) -> 0
C89: Pre-Tax Cash Flow Available for Debt Service (CFADS Pre-Tax used for Sculpting, DSRA and Equity Withdrawls): | D89: £ M | G89: =G79+G81+G82 -> 0 | H89: =H79+H81+H82 -> 0 | I89: =I79+I81+I82 -> 0 | J89: =J79+J81+J82 -> 0 | K89: =K79+K81+K82 -> 0 | L89: =L79+L81+L82 -> 0 | M89: =M79+M81+M82 -> 3.508592 | N89: =N79+N81+N82 -> 15.254421 | ... FA89: =FA79+FA81+FA82 -> 0
C90: (-) Pre-COD CFADS Swept to Construction Loan (Early Repayment) | D90: £ M | G90: =IF(G5<=Debt_Refinance_Date, -G89,0) -> 0 | H90: =IF(H5<=Debt_Refinance_Date, -H89,0) -> 0 | I90: =IF(I5<=Debt_Refinance_Date, -I89,0) -> 0 | J90: =IF(J5<=Debt_Refinance_Date, -J89,0) -> 0 | K90: =IF(K5<=Debt_Refinance_Date, -K89,0) -> 0 | L90: =IF(L5<=Debt_Refinance_Date, -L89,0) -> 0 | M90: =IF(M5<=Debt_Refinance_Date, -M89,0) -> -3.508592 | N90: =IF(N5<=Debt_Refinance_Date, -N89,0) -> -15.254421 | ... FA90: =IF(FA5<=Debt_Refinance_Date, -FA89,0) -> 0
C91: (-) Interest Expense: | D91: £ M | G91: =G68 -> 0 | H91: =H68 -> 0 | I91: =I68 -> 0 | J91: =J68 -> 0 | K91: =K68 -> 0 | L91: =L68 -> 0 | M91: =M68 -> 0 | N91: =N68 -> 0 | ... FA91: =FA68 -> 0
C92: (-) Debt Amortization (Sculpted): | D92: £ M | G92: =-G195 -> 0 | H92: =-H195 -> 0 | I92: =-I195 -> 0 | J92: =-J195 -> 0 | K92: =-K195 -> 0 | L92: =-L195 -> 0 | M92: =-M195 -> 0 | N92: =-N195 -> 0 | ... FA92: =-FA195 -> 0
C93: Cash Flow Post Debt Service (CFPDS) | D93: £ M | G93: =SUM(G89:G92) -> 0 | H93: =SUM(H89:H92) -> 0 | I93: =SUM(I89:I92) -> 0 | J93: =SUM(J89:J92) -> 0 | K93: =SUM(K89:K92) -> 0 | L93: =SUM(L89:L92) -> 0 | M93: =SUM(M89:M92) -> 0 | N93: =SUM(N89:N92) -> 0 | ... FA93: =SUM(FA89:FA92) -> 0
C94: (-) DSRA Funding | D94: £ M | G94: =-G117 -> 0 | H94: =-H117 -> 0 | I94: =-I117 -> 0 | J94: =-J117 -> 0 | K94: =-K117 -> 0 | L94: =-L117 -> 0 | M94: =-M117 -> 0 | N94: =-N117 -> 0 | ... FA94: =-FA117 -> 0
C95: (+) DSRA Withdrawls | D95: £ M | G95: =-G118 -> 0 | H95: =H118 -> 0 | I95: =I118 -> 0 | J95: =J118 -> 0 | K95: =K118 -> 0 | L95: =L118 -> 0 | M95: =M118 -> 0 | N95: =N118 -> 0 | O95: =O118 -> 0 | ... FA95: =FA118 -> 0
C96: (+) Excess DSRA Release to Cash Flow | D96: £ M | G96: =G121 -> 0 | H96: =H121 -> 0 | I96: =I121 -> 0 | J96: =J121 -> 0 | K96: =K121 -> 0 | L96: =L121 -> 0 | M96: =M121 -> 0 | N96: =N121 -> 0 | ... FA96: =FA121 -> 0
C97: Cash Flow Post DSRA (without Cash Withheld): | D97: £ M | G97: =SUM(G93:G96) -> 0 | H97: =SUM(H93:H96) -> 0 | I97: =SUM(I93:I96) -> 0 | J97: =SUM(J93:J96) -> 0 | K97: =SUM(K93:K96) -> 0 | L97: =SUM(L93:L96) -> 0 | M97: =SUM(M93:M96) -> 0 | N97: =SUM(N93:N96) -> 0 | ... FA97: =SUM(FA93:FA96) -> 0
C98: (-) DSRA Cash Withheld: | D98: £ M | G98: =IF(G122<G114-0.01,MAX(0,G97)*-1,0) -> 0 | H98: =IF(H122<H114-0.01,MAX(0,H97)*-1,0) -> 0 | I98: =IF(I122<I114-0.01,MAX(0,I97)*-1,0) -> 0 | J98: =IF(J122<J114-0.01,MAX(0,J97)*-1,0) -> 0 | K98: =IF(K122<K114-0.01,MAX(0,K97)*-1,0) -> 0 | L98: =IF(L122<L114-0.01,MAX(0,L97)*-1,0) -> 0 | M98: =IF(M122<M114-0.01,MAX(0,M97)*-1,0) -> 0 | N98: =IF(N122<N114-0.01,MAX(0,N97)*-1,0) -> 0 | ... FA98: =IF(FA122<FA114-0.01,MAX(0,FA97)*-1,0) -> 0
C99: Cash Flow Post-DSRA Funding: | D99: £ M | G99: =SUM(G97:G98) -> 0 | H99: =SUM(H97:H98) -> 0 | I99: =SUM(I97:I98) -> 0 | J99: =SUM(J97:J98) -> 0 | K99: =SUM(K97:K98) -> 0 | L99: =SUM(L97:L98) -> 0 | M99: =SUM(M97:M98) -> 0 | N99: =SUM(N97:N98) -> 0 | ... FA99: =SUM(FA97:FA98) -> 0
C100: (-) MMRA Funding: | D100: £ M | G100: =-G129 -> 0 | H100: =-H129 -> 0 | I100: =-I129 -> 0 | J100: =-J129 -> 0 | K100: =-K129 -> 0 | L100: =-L129 -> 0 | M100: =-M129 -> 0 | N100: =-N129 -> 0 | ... FA100: =-FA129 -> 0
C101: Cash Flow Post-MMRA Funding: | D101: £ M | G101: =SUM(G99:G100) -> 0 | H101: =SUM(H99:H100) -> 0 | I101: =SUM(I99:I100) -> 0 | J101: =SUM(J99:J100) -> 0 | K101: =SUM(K99:K100) -> 0 | L101: =SUM(L99:L100) -> 0 | M101: =SUM(M99:M100) -> 0 | N101: =SUM(N99:N100) -> 0 | ... FA101: =SUM(FA99:FA100) -> 0
C102: (-) DRA Funding: | D102: £ M | G102: =-G138 -> 0 | H102: =-H138 -> 0 | I102: =-I138 -> 0 | J102: =-J138 -> 0 | K102: =-K138 -> 0 | L102: =-L138 -> 0 | M102: =-M138 -> 0 | N102: =-N138 -> 0 | ... FA102: =-FA138 -> 0
C103: Cash Flow Post Decomissioning Reserve Funding: | D103: £ M | G103: =SUM(G101:G102) -> 0 | H103: =SUM(H101:H102) -> 0 | I103: =SUM(I101:I102) -> 0 | J103: =SUM(J101:J102) -> 0 | K103: =SUM(K101:K102) -> 0 | L103: =SUM(L101:L102) -> 0 | M103: =SUM(M101:M102) -> 0 | N103: =SUM(N101:N102) -> 0 | ... FA103: =SUM(FA101:FA102) -> 0
C104: (-) DSCR Extra Injection: | D104: £ M | G104: =-G142 -> 0 | H104: =-H142 -> 0 | I104: =-I142 -> 0 | J104: =-J142 -> 0 | K104: =-K142 -> 0 | L104: =-L142 -> 0 | M104: =-M142 -> 0 | N104: =-N142 -> 0 | ... FA104: =-FA142 -> 0
C105: (-) DSCR Cash Sweep: | D105: £ M | G105: =-G143 -> 0 | H105: =-H143 -> 0 | I105: =-I143 -> 0 | J105: =-J143 -> 0 | K105: =-K143 -> 0 | L105: =-L143 -> 0 | M105: =-M143 -> 0 | N105: =-N143 -> 0 | ... FA105: =-FA143 -> 0
C106: (-) DSCR Lock Up (No Distribution): | D106: £ M | G106: =-G144 -> 0 | H106: =-H144 -> 0 | I106: =-I144 -> 0 | J106: =-J144 -> 0 | K106: =-K144 -> 0 | L106: =-L144 -> 0 | M106: =-M144 -> 0 | N106: =-N144 -> 0 | ... FA106: =-FA144 -> 0
C107: (+) DSCR Lock Up (Distribution to Equity Investors): | D107: £ M | G107: =G149 -> 0 | H107: =H149 -> 0 | I107: =I149 -> 0 | J107: =J149 -> 0 | K107: =K149 -> 0 | L107: =L149 -> 0 | M107: =M149 -> 0 | N107: =N149 -> 0 | ... FA107: =FA149 -> 0
C108: Actual Cash to Equity Investors Distributed after DSCR Covenants: | D108: £ M | G108: =SUM(G103:G107) -> 0 | H108: =SUM(H103:H107) -> 0 | I108: =SUM(I103:I107) -> 0 | J108: =SUM(J103:J107) -> 0 | K108: =SUM(K103:K107) -> 0 | L108: =SUM(L103:L107) -> 0 | M108: =SUM(M103:M107) -> 0 | N108: =SUM(N103:N107) -> 0 | ... FA108: =SUM(FA103:FA107) -> 0
C110: Maximum Debt Service Allowed: | D110: £ M | G110: =MAX(G89/Min_LLCR,0) -> 0 | H110: =MAX(H89/Min_LLCR,0) -> 0 | I110: =MAX(I89/Min_LLCR,0) -> 0 | J110: =MAX(J89/Min_LLCR,0) -> 0 | K110: =MAX(K89/Min_LLCR,0) -> 0 | L110: =MAX(L89/Min_LLCR,0) -> 0 | M110: =MAX(M89/Min_LLCR,0) -> 2.6989169 | N110: =MAX(N89/Min_LLCR,0) -> 11.73417 | ... FA110: =MAX(FA89/Min_LLCR,0) -> 0
C112: Debt Service Reserve Account
C113: Opening Balance: | D113: £ M | G113: =F122+IF(G56<=Debt_Refinance_Date,Constr_Phase_Model!G16,0) -> 0 | H113: =G122+IF(H56<=Debt_Refinance_Date,Constr_Phase_Model!H16,0) -> 0 | I113: =H122+IF(I56<=Debt_Refinance_Date,Constr_Phase_Model!I16,0) -> 0 | J113: =I122+IF(J56<=Debt_Refinance_Date,Constr_Phase_Model!J16,0) -> 0 | K113: =J122+IF(K56<=Debt_Refinance_Date,Constr_Phase_Model!K16,0) -> 0 | L113: =K122+IF(L56<=Debt_Refinance_Date,Constr_Phase_Model!L16,0) -> 0 | M113: =L122+IF(M56<=Debt_Refinance_Date,Constr_Phase_Model!M16,0) -> 0 | N113: =M122+IF(N56<=Debt_Refinance_Date,Constr_Phase_Model!N16,0) -> 0 | ... FA113: =EZ122+IF(FA56<=Debt_Refinance_Date,Constr_Phase_Model!FA16,0) -> 0
C114: Target Balance Required: | D114: £ M | G114: =(SUM(H84:I84)+SUM(H85:I85))*-1 -> 0 | H114: =(SUM(I84:J84)+SUM(I85:J85))*-1 -> 0 | I114: =(SUM(J84:K84)+SUM(J85:K85))*-1 -> 0 | J114: =(SUM(K84:L84)+SUM(K85:L85))*-1 -> 0 | K114: =(SUM(L84:M84)+SUM(L85:M85))*-1 -> 0 | L114: =(SUM(M84:N84)+SUM(M85:N85))*-1 -> 0 | M114: =(SUM(N84:O84)+SUM(N85:O85))*-1 -> 0 | N114: =(SUM(O84:P84)+SUM(O85:P85))*-1 -> 0 | ... FA114: =(SUM(FB84:FC84)+SUM(FB85:FC85))*-1 -> 0
C115: DSRA Top Needed: | D115: £ M | G115: =MAX(0,G114-G113) -> 0 | H115: =MAX(0,H114-H113) -> 0 | I115: =MAX(0,I114-I113) -> 0 | J115: =MAX(0,J114-J113) -> 0 | K115: =MAX(0,K114-K113) -> 0 | L115: =MAX(0,L114-L113) -> 0 | M115: =MAX(0,M114-M113) -> 0 | N115: =MAX(0,N114-N113) -> 0 | ... FA115: =MAX(0,FA114-FA113) -> 0
C117: DSRA Funding Available (Based on Balance Difference and CFADS): | D117: £ M | G117: =MIN(MAX(0,G114-G113),MAX(0,G93)) -> 0 | H117: =MIN(MAX(0,H114-H113),MAX(0,H93)) -> 0 | I117: =MIN(MAX(0,I114-I113),MAX(0,I93)) -> 0 | J117: =MIN(MAX(0,J114-J113),MAX(0,J93)) -> 0 | K117: =MIN(MAX(0,K114-K113),MAX(0,K93)) -> 0 | L117: =MIN(MAX(0,L114-L113),MAX(0,L93)) -> 0 | M117: =MIN(MAX(0,M114-M113),MAX(0,M93)) -> 0 | N117: =MIN(MAX(0,N114-N113),MAX(0,N93)) -> 0 | ... FA117: =MIN(MAX(0,FA114-FA113),MAX(0,FA93)) -> 0
C118: DSRA Withdrawl to Service Debt in this Quarter: | D118: £ M | G118: =MIN(MAX(0,-G93),G113) -> 0 | H118: =MIN(MAX(0,-H93),H113) -> 0 | I118: =MIN(MAX(0,-I93),I113) -> 0 | J118: =MIN(MAX(0,-J93),J113) -> 0 | K118: =MIN(MAX(0,-K93),K113) -> 0 | L118: =MIN(MAX(0,-L93),L113) -> 0 | M118: =MIN(MAX(0,-M93),M113) -> 0 | N118: =MIN(MAX(0,-N93),N113) -> 0 | ... FA118: =MIN(MAX(0,-FA93),FA113) -> 0
C119: Closing Balance before Excess Cash Release: | D119: £ M | G119: =G113+G117-G118 -> 0 | H119: =H113+H117-H118 -> 0 | I119: =I113+I117-I118 -> 0 | J119: =J113+J117-J118 -> 0 | K119: =K113+K117-K118 -> 0 | L119: =L113+L117-L118 -> 0 | M119: =M113+M117-M118 -> 0 | N119: =N113+N117-N118 -> 0 | ... FA119: =FA113+FA117-FA118 -> 0
C121: Max Excess DSRA Release to Cash Flow in this Quarter: | D121: £ M | G121: =MAX(G119-G114,0) -> 0 | H121: =MAX(H119-H114,0) -> 0 | I121: =MAX(I119-I114,0) -> 0 | J121: =MAX(J119-J114,0) -> 0 | K121: =MAX(K119-K114,0) -> 0 | L121: =MAX(L119-L114,0) -> 0 | M121: =MAX(M119-M114,0) -> 0 | N121: =MAX(N119-N114,0) -> 0 | ... FA121: =MAX(FA119-FA114,0) -> 0
C122: Closing Balance: | D122: £ M | F122: 0 | G122: =G119-G121 -> 0 | H122: =H119-H121 -> 0 | I122: =I119-I121 -> 0 | J122: =J119-J121 -> 0 | K122: =K119-K121 -> 0 | L122: =L119-L121 -> 0 | M122: =M119-M121 -> 0 | N122: =N119-N121 -> 0 | ... FA122: =FA119-FA121 -> 0
C124: Major Maintenance Reserve Account
...

Sheet Sensitivity_Table
B2: Scenario | C2: Value | D2: Case | F2: Construction Period Debt | G2: Construction Period Gearing Ratio | H2: Operation Period Debt | I2: Operations Period Gearing Ratio | K2: Total Invest Equity | L2: Equity IRR | M2: Cash on cash multiple | N2: Net Refinancing Proceeds | O2: Terminal Value at Exit | Q2: Median DSCR | R2: Minimum DSCR
B4: Base P50 | C4: - | D4: P50 | F4: 1625.2044 | G4: 0.65 | H4: 2073.8317 | I4: 0.69237364 | K4: 1196.7367 | L4: 0.10405264 | M4: 1.5662523 | N4: 739.0386 | O4: 2781.2733 | Q4: 1.2998264 | R4: 1.1862792 | T4: Base case: Capex contigency of 2.5%, Construction Capex of 2524 (£/kW), Infrastructure Capex of 550 (£/kW), O&M Opex of 41 (£ / MW / Year), Connection & UoS Opex of 72 (£ / MW / Year), Construction Debt Interest Rate of 5.85%, First Lien Interest Rate of 5.9%, Second Lien Interest Rate of 6.6%, Electricity Rate Escalation Factor of 2%, Annual Degradation Factor of 0.2%
B5: Base P75 | C5: - | D5: P75 | F5: 1621.8698 | G5: 0.65 | H5: 1914.7488 | I5: 0.67504477 | K5: 1197.0469 | L5: 0.06401144 | M5: 1.3450815 | N5: 552.34159 | O5: 2573.826 | Q5: 1.2998277 | R5: 1.1756393
B6: Base P90 | C6: - | D6: P90 | F6: 1618.8685 | G6: 0.65 | H6: 1771.5691 | I6: 0.65770148 | K6: 1197.3262 | L6: 0.027292004 | M6: 1.1460508 | N6: 384.30846 | O6: 2387.117 | Q6: 1.299829 | R6: 1.1644297
B7: Base P99 | C7: - | D7: P99 | F7: 1613.7031 | G7: 0.65 | H7: 1525.1468 | I7: 0.62311049 | K7: 1197.8068 | L7: -0.03706113 | M7: 0.80369804 | N7: 95.111558 | O7: 2065.7776 | Q7: 1.2998319 | R7: 1.1402109
B9: Capex Contigency - 1 | C9: 0.02 | D9: P50 | F9: 1617.4868 | G9: 0.65 | H9: 2073.8317 | I9: 0.6934189 | K9: 1192.2216 | L9: 0.10633513 | M9: 1.579217 | N9: 747.42369 | O9: 2781.2733 | Q9: 1.2998264 | R9: 1.1862792
B10: Capex Contigency - 1 | C10: 0.02 | D10: P75 | F10: 1614.1521 | G10: 0.65 | H10: 1914.7488 | I10: 0.67612101 | K10: 1192.5319 | L10: 0.066208795 | M10: 1.3572054 | N10: 560.72668 | O10: 2573.826 | Q10: 1.2998277 | R10: 1.1756393
B11: Capex Contigency - 1 | C11: 0.02 | D11: P90 | F11: 1611.1509 | G11: 0.65 | H11: 1771.5691 | I11: 0.65880578 | K11: 1192.8111 | L11: 0.029397383 | M11: 1.1574185 | N11: 392.69354 | O11: 2387.117 | Q11: 1.299829 | R11: 1.1644297
B12: Capex Contigency - 1 | C12: 0.02 | D12: P99 | F12: 1605.9855 | G12: 0.65 | H12: 1525.1468 | I12: 0.62426204 | K12: 1193.2918 | L12: -0.035145129 | M12: 0.81376583 | N12: 103.49664 | O12: 2065.7776 | Q12: 1.2998319 | R12: 1.1402109
B14: Capex Contigency - 2 | C14: 0.05 | D14: P50 | F14: 1663.7927 | G14: 0.65 | H14: 2073.8317 | I14: 0.68719425 | K14: 1219.3119 | L14: 0.092817315 | M14: 1.5028691 | N14: 697.11319 | O14: 2781.2733 | Q14: 1.2998264 | R14: 1.1862792
B15: Capex Contigency - 2 | C15: 0.05 | D15: P75 | F15: 1660.4581 | G15: 0.65 | H15: 1914.7488 | I15: 0.66971458 | K15: 1219.6222 | L15: 0.053211507 | M15: 1.2858083 | N15: 510.41618 | O15: 2573.826 | Q15: 1.2998277 | R15: 1.1756393
B16: Capex Contigency - 2 | C16: 0.05 | D16: P90 | F16: 1657.4568 | G16: 0.65 | H16: 1771.5691 | I16: 0.65223501 | K16: 1219.9014 | L16: 0.016957626 | M16: 1.0904743 | N16: 342.38305 | O16: 2387.117 | Q16: 1.299829 | R16: 1.1644297
B17: Capex Contigency - 2 | C17: 0.05 | D17: P99 | F17: 1652.2914 | G17: 0.65 | H17: 1525.1468 | I17: 0.61741589 | K17: 1220.382 | L17: -0.046447875 | M17: 0.75447651 | N17: 53.186144 | O17: 2065.7776 | Q17: 1.2998319 | R17: 1.1402109
B19: Construction Capex - 1 | C19: 2148 | D19: P50 | F19: 1431.6854 | G19: 0.65 | H19: 2073.8317 | I19: 0.71945843 | K19: 1083.9773 | L19: 0.16409104 | M19: 1.9223667 | N19: 948.44891 | O19: 2781.2733 | Q19: 1.2998264 | R19: 1.1862792
B20: Construction Capex - 1 | C20: 2148 | D20: P75 | F20: 1428.3508 | G20: 0.65 | H20: 1914.7488 | I20: 0.702991 | K20: 1084.2875 | L20: 0.12234246 | M20: 1.6780936 | N20: 761.7519 | O20: 2573.826 | Q20: 1.2998277 | R20: 1.1756393
B21: Construction Capex - 1 | C21: 2148 | D21: P90 | F21: 1425.3495 | G21: 0.65 | H21: 1771.5691 | I21: 0.68643735 | K21: 1084.5668 | L21: 0.08364118 | M21: 1.4582845 | N21: 593.71877 | O21: 2387.117 | Q21: 1.299829 | R21: 1.1644297
B22: Construction Capex - 1 | C22: 2148 | D22: P99 | F22: 1420.1841 | G22: 0.65 | H22: 1525.1468 | I22: 0.6532027 | K22: 1085.0474 | L22: 0.014890358 | M22: 1.0802157 | N22: 304.52186 | O22: 2065.7776 | Q22: 1.2998319 | R22: 1.1402109
... B107: Annual Degradation Factor - 2 | C107: 0.005 | D107: P99 | F107: 1612.8127 | G107: 0.65 | H107: 1448.583 | I107: 0.61094405 | K107: 1197.7927 | L107: -0.044533492 | M107: 0.75869005 | N107: 19.192625 | O107: 2002.8378 | Q107: 1.2998462 | R107: 1.1888377

Sheet Data_for_Graphs
B2: Scenario | C2: Value | D2: Case | F2: Construction Period Debt | G2: Construction Period Gearing Ratio | H2: Operation Period Debt | I2: Operations Period Gearing Ratio | K2: Total Invest Equity | L2: Equity IRR | M2: Cash on cash multiple | N2: Net Refinancing Proceeds | O2: Terminal Value at Exit | Q2: Median DSCR | R2: Minimum DSCR
B4: Base P50 | C4: - | D4: P50 | F4: 1625.2044 | G4: 0.65 | H4: 2073.8317 | I4: 0.69237364 | K4: 1196.7367 | L4: 0.10405264 | M4: 1.5662523 | N4: 739.0386 | O4: 2781.2733 | Q4: 1.2998264 | R4: 1.1862792 | T4: Base case: Capex contigency of 2.5%, Construction Capex of 2524 (£/kW), Infrastructure Capex of 550 (£/kW), O&M Opex of 41 (£ / MW / Year), Connection & UoS Opex of 72 (£ / MW / Year), Construction Debt Interest Rate of 5.85%, First Lien Interest Rate of 5.9%, Second Lien Interest Rate of 6.6%, Electricity Rate Escalation Factor of 2%, Annual Degradation Factor of 0.2%
B5: Base P75 | C5: - | D5: P75 | F5: 1621.8698 | G5: 0.65 | H5: 1914.7488 | I5: 0.67504477 | K5: 1197.0469 | L5: 0.06401144 | M5: 1.3450815 | N5: 552.34159 | O5: 2573.826 | Q5: 1.2998277 | R5: 1.1756393
B6: Base P90 | C6: - | D6: P90 | F6: 1618.8685 | G6: 0.65 | H6: 1771.5691 | I6: 0.65770148 | K6: 1197.3262 | L6: 0.027292004 | M6: 1.1460508 | N6: 384.30846 | O6: 2387.117 | Q6: 1.299829 | R6: 1.1644297
B7: Base P99 | C7: - | D7: P99 | F7: 1613.7031 | G7: 0.65 | H7: 1525.1468 | I7: 0.62311049 | K7: 1197.8068 | L7: -0.03706113 | M7: 0.80369804 | N7: 95.111558 | O7: 2065.7776 | Q7: 1.2998319 | R7: 1.1402109
B9: Capex Contigency - 1 | C9: 0.02 | D9: P50 | F9: 1617.4868 | G9: 0.65 | H9: 2073.8317 | I9: 0.6934189 | K9: 1192.2216 | L9: 0.10633513 | M9: 1.579217 | N9: 747.42369 | O9: 2781.2733 | Q9: 1.2998264 | R9: 1.1862792
B10: Capex Contigency - 1 | C10: 0.02 | D10: P75 | F10: 1614.1521 | G10: 0.65 | H10: 1914.7488 | I10: 0.67612101 | K10: 1192.5319 | L10: 0.066208795 | M10: 1.3572054 | N10: 560.72668 | O10: 2573.826 | Q10: 1.2998277 | R10: 1.1756393
B11: Capex Contigency - 1 | C11: 0.02 | D11: P90 | F11: 1611.1509 | G11: 0.65 | H11: 1771.5691 | I11: 0.65880578 | K11: 1192.8111 | L11: 0.029397383 | M11: 1.1574185 | N11: 392.69354 | O11: 2387.117 | Q11: 1.299829 | R11: 1.1644297
B12: Capex Contigency - 1 | C12: 0.02 | D12: P99 | F12: 1605.9855 | G12: 0.65 | H12: 1525.1468 | I12: 0.62426204 | K12: 1193.2918 | L12: -0.035145129 | M12: 0.81376583 | N12: 103.49664 | O12: 2065.7776 | Q12: 1.2998319 | R12: 1.1402109
B14: Capex Contigency - 2 | C14: 0.05 | D14: P50 | F14: 1663.7927 | G14: 0.65 | H14: 2073.8317 | I14: 0.68719425 | K14: 1219.3119 | L14: 0.092817315 | M14: 1.5028691 | N14: 697.11319 | O14: 2781.2733 | Q14: 1.2998264 | R14: 1.1862792
B15: Capex Contigency - 2 | C15: 0.05 | D15: P75 | F15: 1660.4581 | G15: 0.65 | H15: 1914.7488 | I15: 0.66971458 | K15: 1219.6222 | L15: 0.053211507 | M15: 1.2858083 | N15: 510.41618 | O15: 2573.826 | Q15: 1.2998277 | R15: 1.1756393
B16: Capex Contigency - 2 | C16: 0.05 | D16: P90 | F16: 1657.4568 | G16: 0.65 | H16: 1771.5691 | I16: 0.65223501 | K16: 1219.9014 | L16: 0.016957626 | M16: 1.0904743 | N16: 342.38305 | O16: 2387.117 | Q16: 1.299829 | R16: 1.1644297
B17: Capex Contigency - 2 | C17: 0.05 | D17: P99 | F17: 1652.2914 | G17: 0.65 | H17: 1525.1468 | I17: 0.61741589 | K17: 1220.382 | L17: -0.046447875 | M17: 0.75447651 | N17: 53.186144 | O17: 2065.7776 | Q17: 1.2998319 | R17: 1.1402109
B19: Construction Capex - 1 | C19: 2148 | D19: P50 | F19: 1431.6854 | G19: 0.65 | H19: 2073.8317 | I19: 0.71945843 | K19: 1083.9773 | L19: 0.16409104 | M19: 1.9223667 | N19: 948.44891 | O19: 2781.2733 | Q19: 1.2998264 | R19: 1.1862792
B20: Construction Capex - 1 | C20: 2148 | D20: P75 | F20: 1428.3508 | G20: 0.65 | H20: 1914.7488 | I20: 0.702991 | K20: 1084.2875 | L20: 0.12234246 | M20: 1.6780936 | N20: 761.7519 | O20: 2573.826 | Q20: 1.2998277 | R20: 1.1756393
B21: Construction Capex - 1 | C21: 2148 | D21: P90 | F21: 1425.3495 | G21: 0.65 | H21: 1771.5691 | I21: 0.68643735 | K21: 1084.5668 | L21: 0.08364118 | M21: 1.4582845 | N21: 593.71877 | O21: 2387.117 | Q21: 1.299829 | R21: 1.1644297
B22: Construction Capex - 1 | C22: 2148 | D22: P99 | F22: 1420.1841 | G22: 0.65 | H22: 1525.1468 | I22: 0.6532027 | K22: 1085.0474 | L22: 0.014890358 | M22: 1.0802157 | N22: 304.52186 | O22: 2065.7776 | Q22: 1.2998319 | R22: 1.1402109
... B107: Annual Degradation Factor - 2 | C107: 0.005 | D107: P99 | F107: 1612.8127 | G107: 0.65 | H107: 1448.583 | I107: 0.61094405 | K107: 1197.7927 | L107: -0.044533492 | M107: 0.75869005 | N107: 19.192625 | O107: 2002.8378 | Q107: 1.2998462 | R107: 1.1888377
C110: P50 | F110: P90
B111: Variable | C111: Favourable | D111: Adverse | F111: Favourable | G111: Adverse
B112: Construction Capex | C112: =Data_for_Graphs!L19-Data_for_Graphs!$L$4 -> 0.0600384 | D112: =Data_for_Graphs!L24-Data_for_Graphs!$L$4 -> -0.074050346 | F112: =Data_for_Graphs!L21-Data_for_Graphs!$L$6 -> 0.056349176 | G112: =Data_for_Graphs!L26-Data_for_Graphs!$L$6 -> -0.0674816
B113: Electricity Rate Escalation Factor | C113: =Data_for_Graphs!L94-Data_for_Graphs!$L$4 -> 0.033826101 | D113: =Data_for_Graphs!L89-Data_for_Graphs!$L$4 -> -0.031086192 | F113: =Data_for_Graphs!L96-Data_for_Graphs!$L$6 -> 0.029230011 | G113: =Data_for_Graphs!L91-Data_for_Graphs!$L$6 -> -0.026579183
B114: Connection & UoS Opex | C114: =Data_for_Graphs!L49-Data_for_Graphs!$L$4 -> 0.019235635 | D114: =Data_for_Graphs!L54-Data_for_Graphs!$L$4 -> -0.032453278 | F114: =Data_for_Graphs!L51-Data_for_Graphs!$L$6 -> 0.019771606 | G114: =Data_for_Graphs!L56-Data_for_Graphs!$L$6 -> -0.03310651
B115: O&M Opex | C115: =Data_for_Graphs!L39-Data_for_Graphs!$L$4 -> 0.016323519 | D115: =Data_for_Graphs!L44-Data_for_Graphs!$L$4 -> -0.029627553 | F115: =Data_for_Graphs!L41-Data_for_Graphs!$L$6 -> 0.016817611 | G115: =Data_for_Graphs!L46-Data_for_Graphs!$L$6 -> -0.030332042
B116: Infrastructure Capex | C116: =Data_for_Graphs!L29-Data_for_Graphs!$L$4 -> 0.012541509 | D116: =Data_for_Graphs!L34-Data_for_Graphs!$L$4 -> -0.019684109 | F116: =Data_for_Graphs!L31-Data_for_Graphs!$L$6 -> 0.011392146 | G116: =Data_for_Graphs!L36-Data_for_Graphs!$L$6 -> -0.01779784
B117: Capex Contigency | C117: =Data_for_Graphs!L9-Data_for_Graphs!$L$4 -> 0.0022824883 | D117: =Data_for_Graphs!L14-Data_for_Graphs!$L$4 -> -0.01123533 | F117: =Data_for_Graphs!L11-Data_for_Graphs!$L$6 -> 0.0021053791 | G117: =Data_for_Graphs!L16-Data_for_Graphs!$L$6 -> -0.010334378
B118: Annual Degradation Factor | C118: =Data_for_Graphs!L99-Data_for_Graphs!$L$4 -> 0.0012184143 | D118: =Data_for_Graphs!L104-Data_for_Graphs!$L$4 -> -0.011860904 | F118: =Data_for_Graphs!L101-Data_for_Graphs!$L$6 -> 0.00098379254 | G118: =Data_for_Graphs!L106-Data_for_Graphs!$L$6 -> -0.0095858991
B119: First Lien Interest Rate | C119: =Data_for_Graphs!L69-Data_for_Graphs!$L$4 -> 0.0024338007 | D119: =Data_for_Graphs!L74-Data_for_Graphs!$L$4 -> -0.0023348927 | F119: =Data_for_Graphs!L71-Data_for_Graphs!$L$6 -> 0.0013691187 | G119: =Data_for_Graphs!L76-Data_for_Graphs!$L$6 -> -0.001300633
B120: Second Lien Interest Rate | C120: =Data_for_Graphs!L79-Data_for_Graphs!$L$4 -> 0.001621604 | D120: =Data_for_Graphs!L84-Data_for_Graphs!$L$4 -> -0.0015913844 | F120: =Data_for_Graphs!L81-Data_for_Graphs!$L$6 -> 0.00091907978 | G120: =Data_for_Graphs!L86-Data_for_Graphs!$L$6 -> -0.00091156363
B121: Construction Debt Interest Rate | C121: =Data_for_Graphs!L59-Data_for_Graphs!$L$4 -> 0.0010831118 | D121: =Data_for_Graphs!L64-Data_for_Graphs!$L$4 -> -0.0023794413 | F121: =Data_for_Graphs!L61-Data_for_Graphs!$L$6 -> 0.0010385394 | G121: =Data_for_Graphs!L66-Data_for_Graphs!$L$6 -> -0.0022792518
B123: Capex Contigency - 3 | C123: 0.1 | D123: P50 | F123: 1740.9693 | G123: 0.65 | H123: 2073.8317 | I123: 0.67706452 | K123: 1264.4623 | L123: 0.071222261 | M123: 1.3828923 | N123: 613.26236 | O123: 2781.2733 | Q123: 1.2998264 | R123: 1.1862792
B124: Capex Contigency - 3 | C124: 0.1 | D124: P75 | F124: 1737.6347 | G124: 0.65 | H124: 1914.7488 | I124: 0.6593028 | K124: 1264.7726 | L124: 0.032527635 | M124: 1.1736097 | N124: 426.56535 | O124: 2573.826 | Q124: 1.2998277 | R124: 1.1756393
B125: Capex Contigency - 3 | C125: 0.1 | D125: P90 | F125: 1734.6334 | G125: 0.65 | H125: 1771.5691 | I125: 0.64157022 | K125: 1265.0519 | L125: -0.0027746633 | M125: 0.98527215 | N125: 258.53222 | O125: 2387.117 | Q125: 1.299829 | R125: 1.1644297
B126: Capex Contigency - 3 | C126: 0.1 | D126: P99 | F126: 1729.468 | G126: 0.65 | H126: 1525.1468 | I126: 0.60633334 | K126: 1296.1972 | L126: -0.064293322 | M126: 0.6693144 | N126: -30.664685 | O126: 2065.7776 | Q126: 1.2998319 | R126: 1.1402109
B128: Case | C128: Terminal Value £m
B129: Electricity Escalation Factor (1.5%) | C129: =O89 -> 2593.6818
B130: Connection & UoS (86.4 k£/MW/a) | C130: =O54 -> 2609.9688
B131: O&M (54.5 k£/MW/a) | C131: =O44 -> 2625.4623
B132: Annual Degradation Factor (0.5 %) | C132: =O104 -> 2705.6702
B133: Base P50 | C133: =O4 -> 2781.2733
B134: Annual Degradation Factor (0.17%) | C134: =O99 -> 2788.8957
B135: O&M (33.5 k£/MW/a) | C135: =O39 -> 2867.835
B136: Connection & UoS (63.4 k£/MW/a) | C136: =O49 -> 2883.5802
B137: Electricity Escalation Factor (2.5%) | C137: =O94 -> 2976.31
B139: Case | C139: Net Refinancing Proceeds (£m) | D139: Net Refinancing Proceeds as % of Total Invested Equity
B140: Construction Capex (3063 £/kW) | C140: =N24 -> 438.8467 | D140: =C140/K24 -> 0.3230666
B141: Electricity Escalation Factor (1.5%) | C141: =N89 -> 533.61103 | D141: =C141/K89 -> 0.44586856
B142: Infrastructure Capex (678 £/kW) | C142: =N34 -> 666.14385 | D142: =C142/K34 -> 0.53895671
B143: Construction Debt Interest (6.4%) | C143: =N64 -> 729.98213 | D143: =C143/K64 -> 0.60750174
B144: Base P50 | C144: =N4 -> 739.0386 | D144: =C144/K4 -> 0.61754489
B145: Construction Debt Interest (5.6%) | C145: =N59 -> 743.14894 | D145: =C145/K59 -> 0.62213008
B146: Infrastructure Capex (472 £/kW) | C146: =N29 -> 783.45884 | D146: =C146/K29 -> 0.66801396
B147: Construction Capex (2148 £/kW) | C147: =N19 -> 948.44891 | D147: =C147/K19 -> 0.87497122
B148: Electricity Escalation Factor (2.5%) | C148: =N94 -> 958.2954 | D148: =C148/K94 -> 0.80079162
C150: P50 | D150: P75 | E150: P90 | F150: P99
B151: Base | C151: {=TRANSPOSE(R4:R7)} -> 1.1862792 | D151: 1.1756393 | E151: 1.1644297 | F151: 1.1402109
B152: Capex Contigency (5%) | C152: {=TRANSPOSE(R14:R17)} -> 1.1862792 | D152: 1.1756393 | E152: 1.1644297 | F152: 1.1402109
B153: Construction Capex (3063 £/kW) | C153: {=TRANSPOSE(R24:R27)} -> 1.1862792 | D153: 1.1756393 | E153: 1.1644297 | F153: 1.1402109
B154: Infrastructure Capex (678 £/kW) | C154: {=TRANSPOSE(R34:R37)} -> 1.1862792 | D154: 1.1756393 | E154: 1.1644297 | F154: 1.1402109
B155: O&M (54.5 k£/MW/a) | C155: {=TRANSPOSE(R44:R47)} -> 1.1622819 | D155: 1.1487705 | E155: 1.1343789 | F155: 1.1027233
B156: Connection & UoS (86.4 k£/MW/a) | C156: {=TRANSPOSE(R54:R57)} -> 1.162437 | D156: 1.1488305 | E156: 1.134318 | F156: 1.1023245
B157: Construction Debt Interest (6.4%) | C157: {=TRANSPOSE(R64:R67)} -> 1.1862792 | D157: 1.1756393 | E157: 1.1644297 | F157: 1.1402109
B158: First Lien Interest (6.2%) | C158: {=TRANSPOSE(R74:R77)} -> 1.168643 | D158: 1.1581307 | E158: 1.1470562 | F158: 1.1231314
B159: Second Lien Interest (6.9%) | C159: {=TRANSPOSE(R74:R77)} -> 1.168643 | D159: 1.1581307 | E159: 1.1470562 | F159: 1.1231314
B160: Electricity Escalation Factor (2.5%) | C160: {=TRANSPOSE(R94:R97)} -> 1.1194495 | D160: 1.1079973 | E160: 1.0960024 | F160: 1.0703307
B161: Annual Degradation Factor (0.17%) | C161: {=TRANSPOSE(R99:R102)} -> 1.181913 | D161: 1.1711908 | E161: 1.1598977 | F161: 1.1355097
C163: P90 | D163: P99
B164: Base | C164: 1.1644297 | D164: 1.1402109
B165: Capex Contigency (5%) | C165: 1.1644297 | D165: 1.1402109
B166: Construction Capex (3063 £/kW) | C166: 1.1644297 | D166: 1.1402109
B167: Infrastructure Capex (678 £/kW) | C167: 1.1644297 | D167: 1.1402109
B168: Construction Debt Interest (6.4%) | C168: 1.1644297 | D168: 1.1402109
B169: Annual Degradation Factor (0.17%) | C169: 1.1598977 | D169: 1.1355097
B170: First Lien Interest (6.2%) | C170: 1.1470562 | D170: 1.1231314
B171: Second Lien Interest (6.9%) | C171: 1.1470562 | D171: 1.1231314
B172: O&M (54.5 k£/MW/a) | C172: 1.1343789 | D172: 1.1027233
B173: Connection & UoS (86.4 k£/MW/a) | C173: 1.134318 | D173: 1.1023245
B174: Electricity Escalation Factor (2.5%) | C174: 1.0960024 | D174: 1.0703307
C176: P50 | D176: P90
B177: Base | C177: =I4 -> 0.69237364 | D177: =I11 -> 0.65880578
B178: Construction Debt Interest (6.4%) | C178: =I64 -> 0.69124822 | D178: =I66 -> 0.65649378
B179: First Lien Interest (6.2%) | C179: =I74 -> 0.68952703 | D179: =I76 -> 0.65470615
B180: Second Lien Interest (6.9%) | C180: =I84 -> 0.69047501 | D180: =I86 -> 0.65570334
B181: Capex Contigency (5%) | C181: =I14 -> 0.68719425 | D181: =I16 -> 0.65223501
B182: Infrastructure Capex (678 £/kW) | C182: =I34 -> 0.68341785 | D182: =I36 -> 0.64825505
B183: Annual Degradation Factor (0.5%) | C183: =I104 -> 0.68263284 | D183: =I106 -> 0.64675709
B184: O&M (54.5 k£/MW/a) | C184: =I44 -> 0.67896332 | D184: =I46 -> 0.64103793
B185: Connection & UoS (86.4 k£/MW/a) | C185: =I54 -> 0.67735556 | D185: =I56 -> 0.63902878
B186: Electricity Escalation Factor (1.5%) | C186: =I89 -> 0.67050421 | D186: =I91 -> 0.63312441
B187: Construction Capex (3063 £/kW) | C187: =I24 -> 0.65692215 | D187: =I26 -> 0.62046718
B189: DSCR | C189: Q1 | D189: Q2 | E189: Q3 | F189: Q4 | G189: Q5 | H189: Q6 | I189: Q7 | J189: Q8 | K189: Q9 | L189: Q10 | M189: Q11 | N189: Q12 | O189: Q13 | P189: Q14 | Q189: Q15 | R189: Q16 | S189: Q17 | T189: Q18 | U189: Q19 | V189: Q20 | W189: Q21 | X189: Q22 | Y189: Q23 | Z189: Q24
B190: Base - P50 DSCR | C190: 1.2998264 | D190: 1.1862792 | E190: 1.2998264 | F190: 1.2998264 | G190: 1.2998264 | H190: 1.2295766 | I190: 1.2998264 | J190: 1.2998264 | K190: 1.2998264 | L190: 1.2715112 | M190: 1.2998264 | N190: 1.2998264 | O190: 1.2998264 | P190: 1.283248 | Q190: 1.2998264 | R190: 1.2998264 | S190: 1.2998264 | T190: 1.2998264 | U190: 1.2998264 | V190: 1.2998264 | W190: 1.2998264 | X190: 1.2998264 | Y190: 1.2998264 | Z190: 1.2998264
B191: Base - P75 DSCR | C191: 1.2998277 | D191: 1.1756393 | E191: 1.2998277 | F191: 1.2998277 | G191: 1.2998277 | H191: 1.2183675 | I191: 1.2998277 | J191: 1.2998277 | K191: 1.2998277 | L191: 1.2661441 | M191: 1.2998277 | N191: 1.2998277 | O191: 1.2998277 | P191: 1.2777368 | Q191: 1.2998277 | R191: 1.2998277 | S191: 1.2998277 | T191: 1.2998277 | U191: 1.2998277 | V191: 1.2998277 | W191: 1.2998277 | X191: 1.2998277 | Y191: 1.2998277 | Z191: 1.2998277
B192: Base - P90 DSCR | C192: 1.299829 | D192: 1.1644297 | E192: 1.299829 | F192: 1.299829 | G192: 1.299829 | H192: 1.2065463 | I192: 1.299829 | J192: 1.299829 | K192: 1.299829 | L192: 1.2536713 | M192: 1.299829 | N192: 1.299829 | O192: 1.299829 | P192: 1.2718413 | Q192: 1.299829 | R192: 1.299829 | S192: 1.299829 | T192: 1.2948433 | U192: 1.299829 | V192: 1.299829 | W192: 1.299829 | X192: 1.299829 | Y192: 1.299829 | Z192: 1.299829
B193: Base - P99 DSCR | C193: 1.2998319 | D193: 1.1402109 | E193: 1.2998319 | F193: 1.2998319 | G193: 1.2998319 | H193: 1.1809645 | I193: 1.2998319 | J193: 1.2998319 | K193: 1.2998319 | L193: 1.2266318 | M193: 1.2998319 | N193: 1.2998319 | O193: 1.2998319 | P193: 1.2493809 | Q193: 1.2998319 | R193: 1.2998319 | S193: 1.2998319 | T193: 1.2816633 | U193: 1.2998319 | V193: 1.2998319 | W193: 1.2998319 | X193: 1.2985097 | Y193: 1.2998319 | Z193: 1.2998319
B194: O&M (54.5 k£/MW/a) - P90 DSCR | C194: 1.299832 | D194: 1.1343789 | E194: 1.299832 | F194: 1.299832 | G194: 1.299832 | H194: 1.1749752 | I194: 1.299832 | J194: 1.299832 | K194: 1.299832 | L194: 1.22048 | M194: 1.299832 | N194: 1.299832 | O194: 1.299832 | P194: 1.2427782 | Q194: 1.299832 | R194: 1.299832 | S194: 1.299832 | T194: 1.2788492 | U194: 1.299832 | V194: 1.299832 | W194: 1.299832 | X194: 1.2956373 | Y194: 1.299832 | Z194: 1.299832
B195: Connection & UoS (86.4 k£/MW/a) - P90 DSCR | C195: 1.2998331 | D195: 1.134318 | E195: 1.2998331 | F195: 1.2998331 | G195: 1.2998331 | H195: 1.1746021 | I195: 1.2998331 | J195: 1.2998331 | K195: 1.2998331 | L195: 1.2197616 | M195: 1.2998331 | N195: 1.2998331 | O195: 1.2998331 | P195: 1.2413975 | Q195: 1.2998331 | R195: 1.2998331 | S195: 1.2998331 | T195: 1.2780656 | U195: 1.2998331 | V195: 1.2998331 | W195: 1.2998331 | X195: 1.2945893 | Y195: 1.2998331 | Z195: 1.2998331
B196: Electricity Escalation Factor (2.5%) - P90 DSCR | C196: 1.2998063 | D196: 1.0960024 | E196: 1.2998063 | F196: 1.2998063 | G196: 1.2998063 | H196: 1.1413653 | I196: 1.2998063 | J196: 1.2998063 | K196: 1.2998063 | L196: 1.192083 | M196: 1.2998063 | N196: 1.2998063 | O196: 1.2998063 | P196: 1.2243337 | Q196: 1.2998063 | R196: 1.2998063 | S196: 1.2998063 | T196: 1.2743678 | U196: 1.2998063 | V196: 1.2998063 | W196: 1.2998063 | X196: 1.2956081 | Y196: 1.2998063 | Z196: 1.2998063
B197: Default DSCR | C197: 1.1 | D197: 1.1 | E197: 1.1 | F197: 1.1 | G197: 1.1 | H197: 1.1 | I197: 1.1 | J197: 1.1 | K197: 1.1 | L197: 1.1 | M197: 1.1 | N197: 1.1 | O197: 1.1 | P197: 1.1 | Q197: 1.1 | R197: 1.1 | S197: 1.1 | T197: 1.1 | U197: 1.1 | V197: 1.1 | W197: 1.1 | X197: 1.1 | Y197: 1.1 | Z197: 1.1
B200: Outstanding Debt (£m) | C200: Y0 | D200: Y1 | E200: Y2 | F200: Y3 | G200: Y4 | H200: Y5 | I200: Y6 | J200: Y7 | K200: Y8 | L200: Y9 | M200: Y10 | N200: Y11 | O200: Y12 | P200: Y13 | Q200: Y14 | R200: Y15 | S200: Y16 | T200: Y17 | U200: Y18 | V200: Y19
...

Sheet Output_PE_Takeaways

Sheet Outputs_Lender_Takeaways
C23: Minimum DSCR
B24: Cases | C24: P50 | D24: P75 | E24: P90 | F24: P99
B25: Base | C25: =Data_for_Graphs!C151 -> 1.1862792 | D25: =Data_for_Graphs!D151 -> 1.1756393 | E25: =Data_for_Graphs!E151 -> 1.1644297 | F25: =Data_for_Graphs!F151 -> 1.1402109
B26: Capex Contingency (5%) | C26: =Data_for_Graphs!C152 -> 1.1862792 | D26: =Data_for_Graphs!D152 -> 1.1756393 | E26: =Data_for_Graphs!E152 -> 1.1644297 | F26: =Data_for_Graphs!F152 -> 1.1402109
B27: Construction Capex (3063 £/kW) | C27: =Data_for_Graphs!C153 -> 1.1862792 | D27: =Data_for_Graphs!D153 -> 1.1756393 | E27: =Data_for_Graphs!E153 -> 1.1644297 | F27: =Data_for_Graphs!F153 -> 1.1402109
B28: Infrastructure Capex (678 £/kW) | C28: =Data_for_Graphs!C154 -> 1.1862792 | D28: =Data_for_Graphs!D154 -> 1.1756393 | E28: =Data_for_Graphs!E154 -> 1.1644297 | F28: =Data_for_Graphs!F154 -> 1.1402109
B29: O&M (54.5 k£/MW/a) | C29: =Data_for_Graphs!C155 -> 1.1622819 | D29: =Data_for_Graphs!D155 -> 1.1487705 | E29: =Data_for_Graphs!E155 -> 1.1343789 | F29: =Data_for_Graphs!F155 -> 1.1027233
B30: Connection & UoS (86.4 k£/MW/a) | C30: =Data_for_Graphs!C156 -> 1.162437 | D30: =Data_for_Graphs!D156 -> 1.1488305 | E30: =Data_for_Graphs!E156 -> 1.134318 | F30: =Data_for_Graphs!F156 -> 1.1023245
B31: Construction Debt Interest (6.4%) | C31: =Data_for_Graphs!C157 -> 1.1862792 | D31: =Data_for_Graphs!D157 -> 1.1756393 | E31: =Data_for_Graphs!E157 -> 1.1644297 | F31: =Data_for_Graphs!F157 -> 1.1402109
B32: First Lien Interest (6.2%) | C32: =Data_for_Graphs!C158 -> 1.168643 | D32: =Data_for_Graphs!D158 -> 1.1581307 | E32: =Data_for_Graphs!E158 -> 1.1470562 | F32: =Data_for_Graphs!F158 -> 1.1231314
B33: Second Lien Interest (6.9%) | C33: =Data_for_Graphs!C159 -> 1.168643 | D33: =Data_for_Graphs!D159 -> 1.1581307 | E33: =Data_for_Graphs!E159 -> 1.1470562 | F33: =Data_for_Graphs!F159 -> 1.1231314
B34: Electricity Escalation Factor (2.5%) | C34: =Data_for_Graphs!C160 -> 1.1194495 | D34: =Data_for_Graphs!D160 -> 1.1079973 | E34: =Data_for_Graphs!E160 -> 1.0960024 | F34: =Data_for_Graphs!F160 -> 1.0703307
B35: Annual Degradation Factor (0.17%) | C35: =Data_for_Graphs!C161 -> 1.181913 | D35: =Data_for_Graphs!D161 -> 1.1711908 | E35: =Data_for_Graphs!E161 -> 1.1598977 | F35: =Data_for_Graphs!F161 -> 1.1355097
